{
  "id": "https://openalex.org/W2000779764",
  "doi": "https://doi.org/10.1016/s1043-2760(02)00566-0",
  "title": "Cortisol, 11β-hydroxysteroid dehydrogenase type 1 and central obesity",
  "display_name": "Cortisol, 11β-hydroxysteroid dehydrogenase type 1 and central obesity",
  "publication_year": 2002,
  "publication_date": "2002-04-01",
  "ids": {
    "openalex": "https://openalex.org/W2000779764",
    "doi": "https://doi.org/10.1016/s1043-2760(02)00566-0",
    "mag": "2000779764",
    "pmid": "https://pubmed.ncbi.nlm.nih.gov/11893517"
  },
  "language": "en",
  "primary_location": {
    "is_oa": false,
    "landing_page_url": "https://doi.org/10.1016/s1043-2760(02)00566-0",
    "pdf_url": null,
    "source": {
      "id": "https://openalex.org/S93802863",
      "display_name": "Trends in Endocrinology and Metabolism",
      "issn_l": "1043-2760",
      "issn": [
        "1043-2760",
        "1879-3061"
      ],
      "is_oa": false,
      "is_in_doaj": false,
      "is_indexed_in_scopus": true,
      "is_core": true,
      "host_organization": "https://openalex.org/P4310320990",
      "host_organization_name": "Elsevier BV",
      "host_organization_lineage": [
        "https://openalex.org/P4310320990"
      ],
      "host_organization_lineage_names": [
        "Elsevier BV"
      ],
      "type": "journal"
    },
    "license": null,
    "license_id": null,
    "version": null,
    "is_accepted": false,
    "is_published": false
  },
  "type": "article",
  "type_crossref": "journal-article",
  "indexed_in": [
    "crossref",
    "pubmed"
  ],
  "open_access": {
    "is_oa": false,
    "oa_status": "closed",
    "oa_url": null,
    "any_repository_has_fulltext": false
  },
  "authorships": [
    {
      "author_position": "first",
      "author": {
        "id": "https://openalex.org/A5050877182",
        "display_name": "Paul M. Stewart",
        "orcid": "https://orcid.org/0000-0002-1749-9640"
      },
      "institutions": [
        {
          "id": "https://openalex.org/I79619799",
          "display_name": "University of Birmingham",
          "ror": "https://ror.org/03angcq70",
          "country_code": "GB",
          "type": "funder",
          "lineage": [
            "https://openalex.org/I79619799"
          ]
        },
        {
          "id": "https://openalex.org/I2799307867",
          "display_name": "Queen Elizabeth Hospital Birmingham",
          "ror": "https://ror.org/048emj907",
          "country_code": "GB",
          "type": "healthcare",
          "lineage": [
            "https://openalex.org/I1308923049",
            "https://openalex.org/I2799307867"
          ]
        }
      ],
      "countries": [
        "GB"
      ],
      "is_corresponding": false,
      "raw_author_name": "Paul M Stewart",
      "raw_affiliation_strings": [
        "Division of Medical Sciences, University of Birmingham, Queen Elizabeth Hospital, Birmingham, UK B15 2TH"
      ],
      "affiliations": [
        {
          "raw_affiliation_string": "Division of Medical Sciences, University of Birmingham, Queen Elizabeth Hospital, Birmingham, UK B15 2TH",
          "institution_ids": [
            "https://openalex.org/I79619799",
            "https://openalex.org/I2799307867"
          ]
        }
      ]
    },
    {
      "author_position": "last",
      "author": {
        "id": "https://openalex.org/A5083236737",
        "display_name": "Jeremy Tomlinson",
        "orcid": "https://orcid.org/0000-0002-3170-8533"
      },
      "institutions": [
        {
          "id": "https://openalex.org/I79619799",
          "display_name": "University of Birmingham",
          "ror": "https://ror.org/03angcq70",
          "country_code": "GB",
          "type": "funder",
          "lineage": [
            "https://openalex.org/I79619799"
          ]
        },
        {
          "id": "https://openalex.org/I2799307867",
          "display_name": "Queen Elizabeth Hospital Birmingham",
          "ror": "https://ror.org/048emj907",
          "country_code": "GB",
          "type": "healthcare",
          "lineage": [
            "https://openalex.org/I1308923049",
            "https://openalex.org/I2799307867"
          ]
        }
      ],
      "countries": [
        "GB"
      ],
      "is_corresponding": false,
      "raw_author_name": "Jeremy W Tomlinson",
      "raw_affiliation_strings": [
        "Division of Medical Sciences, University of Birmingham, Queen Elizabeth Hospital, Birmingham, UK B15 2TH"
      ],
      "affiliations": [
        {
          "raw_affiliation_string": "Division of Medical Sciences, University of Birmingham, Queen Elizabeth Hospital, Birmingham, UK B15 2TH",
          "institution_ids": [
            "https://openalex.org/I79619799",
            "https://openalex.org/I2799307867"
          ]
        }
      ]
    }
  ],
  "institution_assertions": [],
  "countries_distinct_count": 1,
  "institutions_distinct_count": 2,
  "corresponding_author_ids": [],
  "corresponding_institution_ids": [],
  "apc_list": {
    "value": 6830,
    "currency": "USD",
    "value_usd": 6830
  },
  "apc_paid": null,
  "fwci": 2.715,
  "has_fulltext": true,
  "fulltext_origin": "ngrams",
  "cited_by_count": 42,
  "citation_normalized_percentile": {
    "value": 0.817659,
    "is_in_top_1_percent": false,
    "is_in_top_10_percent": false
  },
  "cited_by_percentile_year": {
    "min": 91,
    "max": 92
  },
  "biblio": {
    "volume": "13",
    "issue": "3",
    "first_page": "94",
    "last_page": "96"
  },
  "is_retracted": false,
  "is_paratext": false,
  "primary_topic": {
    "id": "https://openalex.org/T11839",
    "display_name": "Hormonal Regulation and Hypertension",
    "score": 1.0,
    "subfield": {
      "id": "https://openalex.org/subfields/2712",
      "display_name": "Endocrinology, Diabetes and Metabolism"
    },
    "field": {
      "id": "https://openalex.org/fields/27",
      "display_name": "Medicine"
    },
    "domain": {
      "id": "https://openalex.org/domains/4",
      "display_name": "Health Sciences"
    }
  },
  "topics": [
    {
      "id": "https://openalex.org/T11839",
      "display_name": "Hormonal Regulation and Hypertension",
      "score": 1.0,
      "subfield": {
        "id": "https://openalex.org/subfields/2712",
        "display_name": "Endocrinology, Diabetes and Metabolism"
      },
      "field": {
        "id": "https://openalex.org/fields/27",
        "display_name": "Medicine"
      },
      "domain": {
        "id": "https://openalex.org/domains/4",
        "display_name": "Health Sciences"
      }
    },
    {
      "id": "https://openalex.org/T12421",
      "display_name": "Adrenal Hormones and Disorders",
      "score": 0.9953,
      "subfield": {
        "id": "https://openalex.org/subfields/2712",
        "display_name": "Endocrinology, Diabetes and Metabolism"
      },
      "field": {
        "id": "https://openalex.org/fields/27",
        "display_name": "Medicine"
      },
      "domain": {
        "id": "https://openalex.org/domains/4",
        "display_name": "Health Sciences"
      }
    },
    {
      "id": "https://openalex.org/T13012",
      "display_name": "Coenzyme Q10 studies and effects",
      "score": 0.9868,
      "subfield": {
        "id": "https://openalex.org/subfields/1312",
        "display_name": "Molecular Biology"
      },
      "field": {
        "id": "https://openalex.org/fields/13",
        "display_name": "Biochemistry, Genetics and Molecular Biology"
      },
      "domain": {
        "id": "https://openalex.org/domains/1",
        "display_name": "Life Sciences"
      }
    }
  ],
  "keywords": [],
  "concepts": [
    {
      "id": "https://openalex.org/C134018914",
      "wikidata": "https://www.wikidata.org/wiki/Q162606",
      "display_name": "Endocrinology",
      "level": 1,
      "score": 0.5382611
    },
    {
      "id": "https://openalex.org/C166075782",
      "wikidata": "https://www.wikidata.org/wiki/Q171604",
      "display_name": "11β-hydroxysteroid dehydrogenase type 1",
      "level": 4,
      "score": 0.5304389
    },
    {
      "id": "https://openalex.org/C511355011",
      "wikidata": "https://www.wikidata.org/wiki/Q12174",
      "display_name": "Obesity",
      "level": 2,
      "score": 0.5106295
    },
    {
      "id": "https://openalex.org/C126322002",
      "wikidata": "https://www.wikidata.org/wiki/Q11180",
      "display_name": "Internal medicine",
      "level": 1,
      "score": 0.49285626
    },
    {
      "id": "https://openalex.org/C2776317432",
      "wikidata": "https://www.wikidata.org/wiki/Q412547",
      "display_name": "Dehydrogenase",
      "level": 3,
      "score": 0.48828602
    },
    {
      "id": "https://openalex.org/C71924100",
      "wikidata": "https://www.wikidata.org/wiki/Q11190",
      "display_name": "Medicine",
      "level": 0,
      "score": 0.4691279
    },
    {
      "id": "https://openalex.org/C86803240",
      "wikidata": "https://www.wikidata.org/wiki/Q420",
      "display_name": "Biology",
      "level": 0,
      "score": 0.3304765
    },
    {
      "id": "https://openalex.org/C181199279",
      "wikidata": "https://www.wikidata.org/wiki/Q8047",
      "display_name": "Enzyme",
      "level": 2,
      "score": 0.22728291
    },
    {
      "id": "https://openalex.org/C55493867",
      "wikidata": "https://www.wikidata.org/wiki/Q7094",
      "display_name": "Biochemistry",
      "level": 1,
      "score": 0.1841301
    }
  ],
  "mesh": [
    {
      "descriptor_ui": "D000273",
      "descriptor_name": "Adipose Tissue",
      "qualifier_ui": "Q000201",
      "qualifier_name": "enzymology",
      "is_major_topic": true
    },
    {
      "descriptor_ui": "D006854",
      "descriptor_name": "Hydrocortisone",
      "qualifier_ui": "Q000378",
      "qualifier_name": "metabolism",
      "is_major_topic": true
    },
    {
      "descriptor_ui": "D006913",
      "descriptor_name": "Hydroxysteroid Dehydrogenases",
      "qualifier_ui": "Q000378",
      "qualifier_name": "metabolism",
      "is_major_topic": true
    },
    {
      "descriptor_ui": "D009765",
      "descriptor_name": "Obesity",
      "qualifier_ui": "Q000378",
      "qualifier_name": "metabolism",
      "is_major_topic": true
    },
    {
      "descriptor_ui": "D042842",
      "descriptor_name": "11-beta-Hydroxysteroid Dehydrogenases",
      "qualifier_ui": "",
      "qualifier_name": null,
      "is_major_topic": false
    },
    {
      "descriptor_ui": "D017667",
      "descriptor_name": "Adipocytes",
      "qualifier_ui": "Q000201",
      "qualifier_name": "enzymology",
      "is_major_topic": false
    },
    {
      "descriptor_ui": "D017667",
      "descriptor_name": "Adipocytes",
      "qualifier_ui": "Q000378",
      "qualifier_name": "metabolism",
      "is_major_topic": false
    },
    {
      "descriptor_ui": "D017667",
      "descriptor_name": "Adipocytes",
      "qualifier_ui": "",
      "qualifier_name": null,
      "is_major_topic": false
    },
    {
      "descriptor_ui": "D000273",
      "descriptor_name": "Adipose Tissue",
      "qualifier_ui": "Q000166",
      "qualifier_name": "cytology",
      "is_major_topic": false
    },
    {
      "descriptor_ui": "D000273",
      "descriptor_name": "Adipose Tissue",
      "qualifier_ui": "Q000378",
      "qualifier_name": "metabolism",
      "is_major_topic": false
    },
    {
      "descriptor_ui": "D000273",
      "descriptor_name": "Adipose Tissue",
      "qualifier_ui": "",
      "qualifier_name": null,
      "is_major_topic": false
    },
    {
      "descriptor_ui": "D003480",
      "descriptor_name": "Cushing Syndrome",
      "qualifier_ui": "Q000378",
      "qualifier_name": "metabolism",
      "is_major_topic": false
    },
    {
      "descriptor_ui": "D003480",
      "descriptor_name": "Cushing Syndrome",
      "qualifier_ui": "",
      "qualifier_name": null,
      "is_major_topic": false
    },
    {
      "descriptor_ui": "D006801",
      "descriptor_name": "Humans",
      "qualifier_ui": "",
      "qualifier_name": null,
      "is_major_topic": false
    },
    {
      "descriptor_ui": "D006854",
      "descriptor_name": "Hydrocortisone",
      "qualifier_ui": "",
      "qualifier_name": null,
      "is_major_topic": false
    },
    {
      "descriptor_ui": "D006913",
      "descriptor_name": "Hydroxysteroid Dehydrogenases",
      "qualifier_ui": "",
      "qualifier_name": null,
      "is_major_topic": false
    },
    {
      "descriptor_ui": "D009765",
      "descriptor_name": "Obesity",
      "qualifier_ui": "Q000201",
      "qualifier_name": "enzymology",
      "is_major_topic": false
    },
    {
      "descriptor_ui": "D009765",
      "descriptor_name": "Obesity",
      "qualifier_ui": "",
      "qualifier_name": null,
      "is_major_topic": false
    },
    {
      "descriptor_ui": "D017154",
      "descriptor_name": "Stromal Cells",
      "qualifier_ui": "Q000201",
      "qualifier_name": "enzymology",
      "is_major_topic": false
    },
    {
      "descriptor_ui": "D017154",
      "descriptor_name": "Stromal Cells",
      "qualifier_ui": "Q000378",
      "qualifier_name": "metabolism",
      "is_major_topic": false
    },
    {
      "descriptor_ui": "D017154",
      "descriptor_name": "Stromal Cells",
      "qualifier_ui": "",
      "qualifier_name": null,
      "is_major_topic": false
    }
  ],
  "locations_count": 2,
  "locations": [
    {
      "is_oa": false,
      "landing_page_url": "https://doi.org/10.1016/s1043-2760(02)00566-0",
      "pdf_url": null,
      "source": {
        "id": "https://openalex.org/S93802863",
        "display_name": "Trends in Endocrinology and Metabolism",
        "issn_l": "1043-2760",
        "issn": [
          "1043-2760",
          "1879-3061"
        ],
        "is_oa": false,
        "is_in_doaj": false,
        "is_indexed_in_scopus": true,
        "is_core": true,
        "host_organization": "https://openalex.org/P4310320990",
        "host_organization_name": "Elsevier BV",
        "host_organization_lineage": [
          "https://openalex.org/P4310320990"
        ],
        "host_organization_lineage_names": [
          "Elsevier BV"
        ],
        "type": "journal"
      },
      "license": null,
      "license_id": null,
      "version": null,
      "is_accepted": false,
      "is_published": false
    },
    {
      "is_oa": false,
      "landing_page_url": "https://pubmed.ncbi.nlm.nih.gov/11893517",
      "pdf_url": null,
      "source": {
        "id": "https://openalex.org/S4306525036",
        "display_name": "PubMed",
        "issn_l": null,
        "issn": null,
        "is_oa": false,
        "is_in_doaj": false,
        "is_indexed_in_scopus": false,
        "is_core": false,
        "host_organization": "https://openalex.org/I1299303238",
        "host_organization_name": "National Institutes of Health",
        "host_organization_lineage": [
          "https://openalex.org/I1299303238"
        ],
        "host_organization_lineage_names": [
          "National Institutes of Health"
        ],
        "type": "repository"
      },
      "license": null,
      "license_id": null,
      "version": null,
      "is_accepted": false,
      "is_published": false
    }
  ],
  "best_oa_location": null,
  "sustainable_development_goals": [
    {
      "display_name": "Good health and well-being",
      "id": "https://metadata.un.org/sdg/3",
      "score": 0.71
    }
  ],
  "grants": [],
  "datasets": [],
  "versions": [],
  "referenced_works_count": 15,
  "referenced_works": [
    "https://openalex.org/W1969503127",
    "https://openalex.org/W1987840607",
    "https://openalex.org/W1996744282",
    "https://openalex.org/W2021943148",
    "https://openalex.org/W2099672556",
    "https://openalex.org/W2117268230",
    "https://openalex.org/W2129546749",
    "https://openalex.org/W2149870165",
    "https://openalex.org/W2165935278",
    "https://openalex.org/W2408848216",
    "https://openalex.org/W4242179516",
    "https://openalex.org/W4244655039",
    "https://openalex.org/W4248282367",
    "https://openalex.org/W4254349083",
    "https://openalex.org/W63938293"
  ],
  "related_works": [
    "https://openalex.org/W4239352026",
    "https://openalex.org/W2277004805",
    "https://openalex.org/W2145248244",
    "https://openalex.org/W2132898409",
    "https://openalex.org/W2049142593",
    "https://openalex.org/W2040058909",
    "https://openalex.org/W2037631372",
    "https://openalex.org/W2030889776",
    "https://openalex.org/W1979139803",
    "https://openalex.org/W1966504330"
  ],
  "abstract_inverted_index": null,
  "abstract_inverted_index_v3": null,
  "cited_by_api_url": "https://api.openalex.org/works?filter=cites:W2000779764",
  "counts_by_year": [
    {
      "year": 2024,
      "cited_by_count": 1
    },
    {
      "year": 2023,
      "cited_by_count": 1
    },
    {
      "year": 2019,
      "cited_by_count": 1
    },
    {
      "year": 2017,
      "cited_by_count": 2
    },
    {
      "year": 2016,
      "cited_by_count": 4
    },
    {
      "year": 2015,
      "cited_by_count": 1
    },
    {
      "year": 2014,
      "cited_by_count": 1
    },
    {
      "year": 2013,
      "cited_by_count": 2
    }
  ],
  "updated_date": "2025-05-16T11:12:28.129164",
  "created_date": "2016-06-24"
}