{
  "id": "https://openalex.org/W2009123635",
  "doi": "https://doi.org/10.1007/s12253-010-9330-2",
  "title": "Giant Bilateral Symptomatic Adrenal Myelolipomas Associated with Congenital Adrenal Hyperplasia",
  "display_name": "Giant Bilateral Symptomatic Adrenal Myelolipomas Associated with Congenital Adrenal Hyperplasia",
  "publication_year": 2011,
  "publication_date": "2011-01-10",
  "ids": {
    "openalex": "https://openalex.org/W2009123635",
    "doi": "https://doi.org/10.1007/s12253-010-9330-2",
    "mag": "2009123635",
    "pmid": "https://pubmed.ncbi.nlm.nih.gov/21222246"
  },
  "language": "en",
  "primary_location": {
    "is_oa": false,
    "landing_page_url": "https://doi.org/10.1007/s12253-010-9330-2",
    "pdf_url": null,
    "source": {
      "id": "https://openalex.org/S58162561",
      "display_name": "Pathology & Oncology Research",
      "issn_l": "1219-4956",
      "issn": [
        "1219-4956",
        "1532-2807"
      ],
      "is_oa": true,
      "is_in_doaj": true,
      "is_indexed_in_scopus": true,
      "is_core": true,
      "host_organization": "https://openalex.org/P4310319900",
      "host_organization_name": "Springer Science+Business Media",
      "host_organization_lineage": [
        "https://openalex.org/P4310319965",
        "https://openalex.org/P4310319900"
      ],
      "host_organization_lineage_names": [
        "Springer Nature",
        "Springer Science+Business Media"
      ],
      "type": "journal"
    },
    "license": null,
    "license_id": null,
    "version": null,
    "is_accepted": false,
    "is_published": false
  },
  "type": "article",
  "type_crossref": "journal-article",
  "indexed_in": [
    "crossref",
    "pubmed"
  ],
  "open_access": {
    "is_oa": false,
    "oa_status": "closed",
    "oa_url": null,
    "any_repository_has_fulltext": false
  },
  "authorships": [
    {
      "author_position": "first",
      "author": {
        "id": "https://openalex.org/A5014370309",
        "display_name": "Orestis Ioannidis",
        "orcid": "https://orcid.org/0000-0002-0861-8783"
      },
      "institutions": [
        {
          "id": "https://openalex.org/I4210157387",
          "display_name": "G. Papanikolaou General Hospital",
          "ror": "https://ror.org/0463dsf87",
          "country_code": "GR",
          "type": "healthcare",
          "lineage": [
            "https://openalex.org/I4210157387"
          ]
        }
      ],
      "countries": [
        "GR"
      ],
      "is_corresponding": true,
      "raw_author_name": "Orestis Ioannidis",
      "raw_affiliation_strings": [
        "First Surgical Department, General Regional Hospital 'George Papanikolaou', Thessaloniki, Greece"
      ],
      "affiliations": [
        {
          "raw_affiliation_string": "First Surgical Department, General Regional Hospital 'George Papanikolaou', Thessaloniki, Greece",
          "institution_ids": [
            "https://openalex.org/I4210157387"
          ]
        }
      ]
    },
    {
      "author_position": "middle",
      "author": {
        "id": "https://openalex.org/A5044584317",
        "display_name": "Styliani Papaemmanouil",
        "orcid": null
      },
      "institutions": [
        {
          "id": "https://openalex.org/I4210157387",
          "display_name": "G. Papanikolaou General Hospital",
          "ror": "https://ror.org/0463dsf87",
          "country_code": "GR",
          "type": "healthcare",
          "lineage": [
            "https://openalex.org/I4210157387"
          ]
        }
      ],
      "countries": [
        "GR"
      ],
      "is_corresponding": false,
      "raw_author_name": "Styliani Papaemmanouil",
      "raw_affiliation_strings": [
        "Department of Pathology, General Regional Hospital 'George Papanikolaou', Thessaloniki, Greece"
      ],
      "affiliations": [
        {
          "raw_affiliation_string": "Department of Pathology, General Regional Hospital 'George Papanikolaou', Thessaloniki, Greece",
          "institution_ids": [
            "https://openalex.org/I4210157387"
          ]
        }
      ]
    },
    {
      "author_position": "middle",
      "author": {
        "id": "https://openalex.org/A5069787592",
        "display_name": "Stavros Chatzopoulos",
        "orcid": "https://orcid.org/0000-0001-9488-1811"
      },
      "institutions": [
        {
          "id": "https://openalex.org/I4210157387",
          "display_name": "G. Papanikolaou General Hospital",
          "ror": "https://ror.org/0463dsf87",
          "country_code": "GR",
          "type": "healthcare",
          "lineage": [
            "https://openalex.org/I4210157387"
          ]
        }
      ],
      "countries": [
        "GR"
      ],
      "is_corresponding": false,
      "raw_author_name": "Stavros Chatzopoulos",
      "raw_affiliation_strings": [
        "First Surgical Department, General Regional Hospital 'George Papanikolaou', Thessaloniki, Greece"
      ],
      "affiliations": [
        {
          "raw_affiliation_string": "First Surgical Department, General Regional Hospital 'George Papanikolaou', Thessaloniki, Greece",
          "institution_ids": [
            "https://openalex.org/I4210157387"
          ]
        }
      ]
    },
    {
      "author_position": "middle",
      "author": {
        "id": "https://openalex.org/A5077804331",
        "display_name": "George P. Paraskevas",
        "orcid": "https://orcid.org/0000-0002-2481-3060"
      },
      "institutions": [
        {
          "id": "https://openalex.org/I4210157387",
          "display_name": "G. Papanikolaou General Hospital",
          "ror": "https://ror.org/0463dsf87",
          "country_code": "GR",
          "type": "healthcare",
          "lineage": [
            "https://openalex.org/I4210157387"
          ]
        }
      ],
      "countries": [
        "GR"
      ],
      "is_corresponding": false,
      "raw_author_name": "George Paraskevas",
      "raw_affiliation_strings": [
        "First Surgical Department, General Regional Hospital 'George Papanikolaou', Thessaloniki, Greece"
      ],
      "affiliations": [
        {
          "raw_affiliation_string": "First Surgical Department, General Regional Hospital 'George Papanikolaou', Thessaloniki, Greece",
          "institution_ids": [
            "https://openalex.org/I4210157387"
          ]
        }
      ]
    },
    {
      "author_position": "middle",
      "author": {
        "id": "https://openalex.org/A5061438890",
        "display_name": "Athina Konstantara",
        "orcid": null
      },
      "institutions": [
        {
          "id": "https://openalex.org/I4210157387",
          "display_name": "G. Papanikolaou General Hospital",
          "ror": "https://ror.org/0463dsf87",
          "country_code": "GR",
          "type": "healthcare",
          "lineage": [
            "https://openalex.org/I4210157387"
          ]
        }
      ],
      "countries": [
        "GR"
      ],
      "is_corresponding": false,
      "raw_author_name": "Athina Konstantara",
      "raw_affiliation_strings": [
        "First Surgical Department, General Regional Hospital 'George Papanikolaou', Thessaloniki, Greece"
      ],
      "affiliations": [
        {
          "raw_affiliation_string": "First Surgical Department, General Regional Hospital 'George Papanikolaou', Thessaloniki, Greece",
          "institution_ids": [
            "https://openalex.org/I4210157387"
          ]
        }
      ]
    },
    {
      "author_position": "middle",
      "author": {
        "id": "https://openalex.org/A5080777153",
        "display_name": "Anastasios Kotronis",
        "orcid": null
      },
      "institutions": [
        {
          "id": "https://openalex.org/I4210157387",
          "display_name": "G. Papanikolaou General Hospital",
          "ror": "https://ror.org/0463dsf87",
          "country_code": "GR",
          "type": "healthcare",
          "lineage": [
            "https://openalex.org/I4210157387"
          ]
        }
      ],
      "countries": [
        "GR"
      ],
      "is_corresponding": false,
      "raw_author_name": "Anastasios Kotronis",
      "raw_affiliation_strings": [
        "First Surgical Department, General Regional Hospital 'George Papanikolaou', Thessaloniki, Greece"
      ],
      "affiliations": [
        {
          "raw_affiliation_string": "First Surgical Department, General Regional Hospital 'George Papanikolaou', Thessaloniki, Greece",
          "institution_ids": [
            "https://openalex.org/I4210157387"
          ]
        }
      ]
    },
    {
      "author_position": "middle",
      "author": {
        "id": "https://openalex.org/A5081005937",
        "display_name": "Emmanouil Kakoutis",
        "orcid": null
      },
      "institutions": [
        {
          "id": "https://openalex.org/I4210157387",
          "display_name": "G. Papanikolaou General Hospital",
          "ror": "https://ror.org/0463dsf87",
          "country_code": "GR",
          "type": "healthcare",
          "lineage": [
            "https://openalex.org/I4210157387"
          ]
        }
      ],
      "countries": [
        "GR"
      ],
      "is_corresponding": false,
      "raw_author_name": "Emmanouil Kakoutis",
      "raw_affiliation_strings": [
        "First Surgical Department, General Regional Hospital 'George Papanikolaou', Thessaloniki, Greece"
      ],
      "affiliations": [
        {
          "raw_affiliation_string": "First Surgical Department, General Regional Hospital 'George Papanikolaou', Thessaloniki, Greece",
          "institution_ids": [
            "https://openalex.org/I4210157387"
          ]
        }
      ]
    },
    {
      "author_position": "last",
      "author": {
        "id": "https://openalex.org/A5041366281",
        "display_name": "Apostolos Makrantonakis",
        "orcid": null
      },
      "institutions": [
        {
          "id": "https://openalex.org/I4210157387",
          "display_name": "G. Papanikolaou General Hospital",
          "ror": "https://ror.org/0463dsf87",
          "country_code": "GR",
          "type": "healthcare",
          "lineage": [
            "https://openalex.org/I4210157387"
          ]
        }
      ],
      "countries": [
        "GR"
      ],
      "is_corresponding": false,
      "raw_author_name": "Apostolos Makrantonakis",
      "raw_affiliation_strings": [
        "First Surgical Department, General Regional Hospital 'George Papanikolaou', Thessaloniki, Greece"
      ],
      "affiliations": [
        {
          "raw_affiliation_string": "First Surgical Department, General Regional Hospital 'George Papanikolaou', Thessaloniki, Greece",
          "institution_ids": [
            "https://openalex.org/I4210157387"
          ]
        }
      ]
    }
  ],
  "institution_assertions": [],
  "countries_distinct_count": 1,
  "institutions_distinct_count": 1,
  "corresponding_author_ids": [
    "https://openalex.org/A5014370309"
  ],
  "corresponding_institution_ids": [
    "https://openalex.org/I4210157387"
  ],
  "apc_list": {
    "value": 2500,
    "currency": "USD",
    "value_usd": 2500
  },
  "apc_paid": null,
  "fwci": 4.032,
  "has_fulltext": true,
  "fulltext_origin": "ngrams",
  "cited_by_count": 43,
  "citation_normalized_percentile": {
    "value": 0.961675,
    "is_in_top_1_percent": false,
    "is_in_top_10_percent": true
  },
  "cited_by_percentile_year": {
    "min": 94,
    "max": 95
  },
  "biblio": {
    "volume": "17",
    "issue": "3",
    "first_page": "775",
    "last_page": "778"
  },
  "is_retracted": false,
  "is_paratext": false,
  "primary_topic": {
    "id": "https://openalex.org/T11054",
    "display_name": "Adrenal and Paraganglionic Tumors",
    "score": 1.0,
    "subfield": {
      "id": "https://openalex.org/subfields/2746",
      "display_name": "Surgery"
    },
    "field": {
      "id": "https://openalex.org/fields/27",
      "display_name": "Medicine"
    },
    "domain": {
      "id": "https://openalex.org/domains/4",
      "display_name": "Health Sciences"
    }
  },
  "topics": [
    {
      "id": "https://openalex.org/T11054",
      "display_name": "Adrenal and Paraganglionic Tumors",
      "score": 1.0,
      "subfield": {
        "id": "https://openalex.org/subfields/2746",
        "display_name": "Surgery"
      },
      "field": {
        "id": "https://openalex.org/fields/27",
        "display_name": "Medicine"
      },
      "domain": {
        "id": "https://openalex.org/domains/4",
        "display_name": "Health Sciences"
      }
    },
    {
      "id": "https://openalex.org/T10631",
      "display_name": "Cancer, Hypoxia, and Metabolism",
      "score": 0.9992,
      "subfield": {
        "id": "https://openalex.org/subfields/1306",
        "display_name": "Cancer Research"
      },
      "field": {
        "id": "https://openalex.org/fields/13",
        "display_name": "Biochemistry, Genetics and Molecular Biology"
      },
      "domain": {
        "id": "https://openalex.org/domains/1",
        "display_name": "Life Sciences"
      }
    },
    {
      "id": "https://openalex.org/T12226",
      "display_name": "Neuroblastoma Research and Treatments",
      "score": 0.9851,
      "subfield": {
        "id": "https://openalex.org/subfields/2728",
        "display_name": "Neurology"
      },
      "field": {
        "id": "https://openalex.org/fields/27",
        "display_name": "Medicine"
      },
      "domain": {
        "id": "https://openalex.org/domains/4",
        "display_name": "Health Sciences"
      }
    }
  ],
  "keywords": [
    {
      "id": "https://openalex.org/keywords/myelolipoma",
      "display_name": "Myelolipoma",
      "score": 0.9183868
    },
    {
      "id": "https://openalex.org/keywords/abdominal-ultrasonography",
      "display_name": "Abdominal ultrasonography",
      "score": 0.48649615
    }
  ],
  "concepts": [
    {
      "id": "https://openalex.org/C2776290861",
      "wikidata": "https://www.wikidata.org/wiki/Q1956552",
      "display_name": "Myelolipoma",
      "level": 3,
      "score": 0.9183868
    },
    {
      "id": "https://openalex.org/C71924100",
      "wikidata": "https://www.wikidata.org/wiki/Q11190",
      "display_name": "Medicine",
      "level": 0,
      "score": 0.8620856
    },
    {
      "id": "https://openalex.org/C2777767042",
      "wikidata": "https://www.wikidata.org/wiki/Q366868",
      "display_name": "Congenital adrenal hyperplasia",
      "level": 2,
      "score": 0.6544098
    },
    {
      "id": "https://openalex.org/C2780801072",
      "wikidata": "https://www.wikidata.org/wiki/Q837512",
      "display_name": "Differential diagnosis",
      "level": 2,
      "score": 0.62182736
    },
    {
      "id": "https://openalex.org/C2780778865",
      "wikidata": "https://www.wikidata.org/wiki/Q1130374",
      "display_name": "Laparotomy",
      "level": 2,
      "score": 0.50873977
    },
    {
      "id": "https://openalex.org/C171089720",
      "wikidata": "https://www.wikidata.org/wiki/Q193583",
      "display_name": "Adipose tissue",
      "level": 2,
      "score": 0.4891129
    },
    {
      "id": "https://openalex.org/C2777655228",
      "wikidata": "https://www.wikidata.org/wiki/Q590460",
      "display_name": "Abdominal ultrasonography",
      "level": 3,
      "score": 0.48649615
    },
    {
      "id": "https://openalex.org/C126838900",
      "wikidata": "https://www.wikidata.org/wiki/Q77604",
      "display_name": "Radiology",
      "level": 1,
      "score": 0.47430137
    },
    {
      "id": "https://openalex.org/C2780694816",
      "wikidata": "https://www.wikidata.org/wiki/Q712294",
      "display_name": "Adrenal gland",
      "level": 2,
      "score": 0.47413254
    },
    {
      "id": "https://openalex.org/C2780955771",
      "wikidata": "https://www.wikidata.org/wiki/Q183425",
      "display_name": "Abdominal pain",
      "level": 2,
      "score": 0.42196885
    },
    {
      "id": "https://openalex.org/C142724271",
      "wikidata": "https://www.wikidata.org/wiki/Q7208",
      "display_name": "Pathology",
      "level": 1,
      "score": 0.41931725
    },
    {
      "id": "https://openalex.org/C2776730994",
      "wikidata": "https://www.wikidata.org/wiki/Q689985",
      "display_name": "Lipoma",
      "level": 2,
      "score": 0.41517252
    },
    {
      "id": "https://openalex.org/C141071460",
      "wikidata": "https://www.wikidata.org/wiki/Q40821",
      "display_name": "Surgery",
      "level": 1,
      "score": 0.2658349
    },
    {
      "id": "https://openalex.org/C126322002",
      "wikidata": "https://www.wikidata.org/wiki/Q11180",
      "display_name": "Internal medicine",
      "level": 1,
      "score": 0.17589056
    },
    {
      "id": "https://openalex.org/C529618451",
      "wikidata": "https://www.wikidata.org/wiki/Q234904",
      "display_name": "Ultrasonography",
      "level": 2,
      "score": 0.10669631
    }
  ],
  "mesh": [
    {
      "descriptor_ui": "D000273",
      "descriptor_name": "Adipose Tissue",
      "qualifier_ui": "Q000473",
      "qualifier_name": "pathology",
      "is_major_topic": true
    },
    {
      "descriptor_ui": "D000310",
      "descriptor_name": "Adrenal Gland Neoplasms",
      "qualifier_ui": "Q000473",
      "qualifier_name": "pathology",
      "is_major_topic": true
    },
    {
      "descriptor_ui": "D000312",
      "descriptor_name": "Adrenal Hyperplasia, Congenital",
      "qualifier_ui": "Q000473",
      "qualifier_name": "pathology",
      "is_major_topic": true
    },
    {
      "descriptor_ui": "D018209",
      "descriptor_name": "Myelolipoma",
      "qualifier_ui": "Q000473",
      "qualifier_name": "pathology",
      "is_major_topic": true
    },
    {
      "descriptor_ui": "D000273",
      "descriptor_name": "Adipose Tissue",
      "qualifier_ui": "",
      "qualifier_name": null,
      "is_major_topic": false
    },
    {
      "descriptor_ui": "D000273",
      "descriptor_name": "Adipose Tissue",
      "qualifier_ui": "Q000000981",
      "qualifier_name": "diagnostic imaging",
      "is_major_topic": false
    },
    {
      "descriptor_ui": "D000273",
      "descriptor_name": "Adipose Tissue",
      "qualifier_ui": "Q000601",
      "qualifier_name": "surgery",
      "is_major_topic": false
    },
    {
      "descriptor_ui": "D000310",
      "descriptor_name": "Adrenal Gland Neoplasms",
      "qualifier_ui": "",
      "qualifier_name": null,
      "is_major_topic": false
    },
    {
      "descriptor_ui": "D000310",
      "descriptor_name": "Adrenal Gland Neoplasms",
      "qualifier_ui": "Q000000981",
      "qualifier_name": "diagnostic imaging",
      "is_major_topic": false
    },
    {
      "descriptor_ui": "D000310",
      "descriptor_name": "Adrenal Gland Neoplasms",
      "qualifier_ui": "Q000601",
      "qualifier_name": "surgery",
      "is_major_topic": false
    },
    {
      "descriptor_ui": "D000312",
      "descriptor_name": "Adrenal Hyperplasia, Congenital",
      "qualifier_ui": "",
      "qualifier_name": null,
      "is_major_topic": false
    },
    {
      "descriptor_ui": "D000312",
      "descriptor_name": "Adrenal Hyperplasia, Congenital",
      "qualifier_ui": "Q000000981",
      "qualifier_name": "diagnostic imaging",
      "is_major_topic": false
    },
    {
      "descriptor_ui": "D000312",
      "descriptor_name": "Adrenal Hyperplasia, Congenital",
      "qualifier_ui": "Q000601",
      "qualifier_name": "surgery",
      "is_major_topic": false
    },
    {
      "descriptor_ui": "D000328",
      "descriptor_name": "Adult",
      "qualifier_ui": "",
      "qualifier_name": null,
      "is_major_topic": false
    },
    {
      "descriptor_ui": "D005260",
      "descriptor_name": "Female",
      "qualifier_ui": "",
      "qualifier_name": null,
      "is_major_topic": false
    },
    {
      "descriptor_ui": "D006801",
      "descriptor_name": "Humans",
      "qualifier_ui": "",
      "qualifier_name": null,
      "is_major_topic": false
    },
    {
      "descriptor_ui": "D008279",
      "descriptor_name": "Magnetic Resonance Imaging",
      "qualifier_ui": "",
      "qualifier_name": null,
      "is_major_topic": false
    },
    {
      "descriptor_ui": "D018209",
      "descriptor_name": "Myelolipoma",
      "qualifier_ui": "Q000000981",
      "qualifier_name": "diagnostic imaging",
      "is_major_topic": false
    },
    {
      "descriptor_ui": "D018209",
      "descriptor_name": "Myelolipoma",
      "qualifier_ui": "Q000601",
      "qualifier_name": "surgery",
      "is_major_topic": false
    },
    {
      "descriptor_ui": "D018209",
      "descriptor_name": "Myelolipoma",
      "qualifier_ui": "",
      "qualifier_name": null,
      "is_major_topic": false
    },
    {
      "descriptor_ui": "D011379",
      "descriptor_name": "Prognosis",
      "qualifier_ui": "",
      "qualifier_name": null,
      "is_major_topic": false
    },
    {
      "descriptor_ui": "D014057",
      "descriptor_name": "Tomography, X-Ray Computed",
      "qualifier_ui": "",
      "qualifier_name": null,
      "is_major_topic": false
    }
  ],
  "locations_count": 2,
  "locations": [
    {
      "is_oa": false,
      "landing_page_url": "https://doi.org/10.1007/s12253-010-9330-2",
      "pdf_url": null,
      "source": {
        "id": "https://openalex.org/S58162561",
        "display_name": "Pathology & Oncology Research",
        "issn_l": "1219-4956",
        "issn": [
          "1219-4956",
          "1532-2807"
        ],
        "is_oa": true,
        "is_in_doaj": true,
        "is_indexed_in_scopus": true,
        "is_core": true,
        "host_organization": "https://openalex.org/P4310319900",
        "host_organization_name": "Springer Science+Business Media",
        "host_organization_lineage": [
          "https://openalex.org/P4310319965",
          "https://openalex.org/P4310319900"
        ],
        "host_organization_lineage_names": [
          "Springer Nature",
          "Springer Science+Business Media"
        ],
        "type": "journal"
      },
      "license": null,
      "license_id": null,
      "version": null,
      "is_accepted": false,
      "is_published": false
    },
    {
      "is_oa": false,
      "landing_page_url": "https://pubmed.ncbi.nlm.nih.gov/21222246",
      "pdf_url": null,
      "source": {
        "id": "https://openalex.org/S4306525036",
        "display_name": "PubMed",
        "issn_l": null,
        "issn": null,
        "is_oa": false,
        "is_in_doaj": false,
        "is_indexed_in_scopus": false,
        "is_core": false,
        "host_organization": "https://openalex.org/I1299303238",
        "host_organization_name": "National Institutes of Health",
        "host_organization_lineage": [
          "https://openalex.org/I1299303238"
        ],
        "host_organization_lineage_names": [
          "National Institutes of Health"
        ],
        "type": "repository"
      },
      "license": null,
      "license_id": null,
      "version": null,
      "is_accepted": false,
      "is_published": false
    }
  ],
  "best_oa_location": null,
  "sustainable_development_goals": [
    {
      "id": "https://metadata.un.org/sdg/14",
      "display_name": "Life below water",
      "score": 0.66
    }
  ],
  "grants": [],
  "datasets": [],
  "versions": [],
  "referenced_works_count": 13,
  "referenced_works": [
    "https://openalex.org/W1510184890",
    "https://openalex.org/W1968007066",
    "https://openalex.org/W2018028623",
    "https://openalex.org/W2020741873",
    "https://openalex.org/W2031586363",
    "https://openalex.org/W2047878489",
    "https://openalex.org/W2100531156",
    "https://openalex.org/W2120939566",
    "https://openalex.org/W2161332932",
    "https://openalex.org/W2343034041",
    "https://openalex.org/W4235177340",
    "https://openalex.org/W4244656881",
    "https://openalex.org/W4256452499"
  ],
  "related_works": [
    "https://openalex.org/W2583369296",
    "https://openalex.org/W2418254113",
    "https://openalex.org/W2418064381",
    "https://openalex.org/W2411449510",
    "https://openalex.org/W2411147166",
    "https://openalex.org/W2407907011",
    "https://openalex.org/W2325565446",
    "https://openalex.org/W2098478800",
    "https://openalex.org/W2036280709",
    "https://openalex.org/W2025034669"
  ],
  "abstract_inverted_index": null,
  "abstract_inverted_index_v3": null,
  "cited_by_api_url": "https://api.openalex.org/works?filter=cites:W2009123635",
  "counts_by_year": [
    {
      "year": 2024,
      "cited_by_count": 2
    },
    {
      "year": 2023,
      "cited_by_count": 6
    },
    {
      "year": 2022,
      "cited_by_count": 3
    },
    {
      "year": 2021,
      "cited_by_count": 3
    },
    {
      "year": 2020,
      "cited_by_count": 2
    },
    {
      "year": 2019,
      "cited_by_count": 2
    },
    {
      "year": 2018,
      "cited_by_count": 5
    },
    {
      "year": 2017,
      "cited_by_count": 1
    },
    {
      "year": 2016,
      "cited_by_count": 4
    },
    {
      "year": 2015,
      "cited_by_count": 2
    },
    {
      "year": 2014,
      "cited_by_count": 6
    },
    {
      "year": 2013,
      "cited_by_count": 1
    },
    {
      "year": 2012,
      "cited_by_count": 4
    }
  ],
  "updated_date": "2025-05-16T14:01:32.500548",
  "created_date": "2016-06-24"
}