{
  "id": "https://openalex.org/W2054692302",
  "doi": "https://doi.org/10.1126/science.277.5332.1659",
  "title": "Maternal Care, Hippocampal Glucocorticoid Receptors, and Hypothalamic-Pituitary-Adrenal Responses to Stress",
  "display_name": "Maternal Care, Hippocampal Glucocorticoid Receptors, and Hypothalamic-Pituitary-Adrenal Responses to Stress",
  "publication_year": 1997,
  "publication_date": "1997-09-12",
  "ids": {
    "openalex": "https://openalex.org/W2054692302",
    "doi": "https://doi.org/10.1126/science.277.5332.1659",
    "mag": "2054692302",
    "pmid": "https://pubmed.ncbi.nlm.nih.gov/9287218"
  },
  "language": "en",
  "primary_location": {
    "is_oa": false,
    "landing_page_url": "https://doi.org/10.1126/science.277.5332.1659",
    "pdf_url": null,
    "source": {
      "id": "https://openalex.org/S3880285",
      "display_name": "Science",
      "issn_l": "0036-8075",
      "issn": [
        "0036-8075",
        "1095-9203"
      ],
      "is_oa": false,
      "is_in_doaj": false,
      "is_indexed_in_scopus": true,
      "is_core": true,
      "host_organization": "https://openalex.org/P4310315823",
      "host_organization_name": "American Association for the Advancement of Science",
      "host_organization_lineage": [
        "https://openalex.org/P4310315823"
      ],
      "host_organization_lineage_names": [
        "American Association for the Advancement of Science"
      ],
      "type": "journal"
    },
    "license": null,
    "license_id": null,
    "version": null,
    "is_accepted": false,
    "is_published": false
  },
  "type": "article",
  "type_crossref": "journal-article",
  "indexed_in": [
    "crossref",
    "pubmed"
  ],
  "open_access": {
    "is_oa": false,
    "oa_status": "closed",
    "oa_url": null,
    "any_repository_has_fulltext": false
  },
  "authorships": [
    {
      "author_position": "first",
      "author": {
        "id": "https://openalex.org/A5100627479",
        "display_name": "Dong Liu",
        "orcid": "https://orcid.org/0000-0001-5498-6352"
      },
      "institutions": [
        {
          "id": "https://openalex.org/I5023651",
          "display_name": "McGill University",
          "ror": "https://ror.org/01pxwe438",
          "country_code": "CA",
          "type": "funder",
          "lineage": [
            "https://openalex.org/I5023651"
          ]
        },
        {
          "id": "https://openalex.org/I2799434747",
          "display_name": "Douglas Mental Health University Institute",
          "ror": "https://ror.org/05dk2r620",
          "country_code": "CA",
          "type": "healthcare",
          "lineage": [
            "https://openalex.org/I2799434747"
          ]
        },
        {
          "id": "https://openalex.org/I150468666",
          "display_name": "Emory University",
          "ror": "https://ror.org/03czfpz43",
          "country_code": "US",
          "type": "funder",
          "lineage": [
            "https://openalex.org/I150468666"
          ]
        }
      ],
      "countries": [
        "CA",
        "US"
      ],
      "is_corresponding": false,
      "raw_author_name": "Dong Liu",
      "raw_affiliation_strings": [
        "D. Liu, J. Diorio, B. Tannenbaum, C. Caldji, D. Francis, A. Freedman, S. Sharma, D. Pearson, M. J. Meaney, Developmental Neuroendocrinology Laboratory, Douglas Hospital Research Center, Departments of Psychiatry, and Neurology and Neurosurgery, Faculty of Medicine, McGill University, Montreal, Canada H4H 1R3.",
        "P. M. Plotsky, Department of Psychiatry and Behavioral Science, Emory University, Atlanta, GA 30322, USA."
      ],
      "affiliations": [
        {
          "raw_affiliation_string": "D. Liu, J. Diorio, B. Tannenbaum, C. Caldji, D. Francis, A. Freedman, S. Sharma, D. Pearson, M. J. Meaney, Developmental Neuroendocrinology Laboratory, Douglas Hospital Research Center, Departments of Psychiatry, and Neurology and Neurosurgery, Faculty of Medicine, McGill University, Montreal, Canada H4H 1R3.",
          "institution_ids": [
            "https://openalex.org/I5023651",
            "https://openalex.org/I2799434747"
          ]
        },
        {
          "raw_affiliation_string": "P. M. Plotsky, Department of Psychiatry and Behavioral Science, Emory University, Atlanta, GA 30322, USA.",
          "institution_ids": [
            "https://openalex.org/I150468666"
          ]
        }
      ]
    },
    {
      "author_position": "middle",
      "author": {
        "id": "https://openalex.org/A5046707379",
        "display_name": "Josie Diorio",
        "orcid": null
      },
      "institutions": [
        {
          "id": "https://openalex.org/I5023651",
          "display_name": "McGill University",
          "ror": "https://ror.org/01pxwe438",
          "country_code": "CA",
          "type": "funder",
          "lineage": [
            "https://openalex.org/I5023651"
          ]
        },
        {
          "id": "https://openalex.org/I2799434747",
          "display_name": "Douglas Mental Health University Institute",
          "ror": "https://ror.org/05dk2r620",
          "country_code": "CA",
          "type": "healthcare",
          "lineage": [
            "https://openalex.org/I2799434747"
          ]
        },
        {
          "id": "https://openalex.org/I150468666",
          "display_name": "Emory University",
          "ror": "https://ror.org/03czfpz43",
          "country_code": "US",
          "type": "funder",
          "lineage": [
            "https://openalex.org/I150468666"
          ]
        }
      ],
      "countries": [
        "CA",
        "US"
      ],
      "is_corresponding": false,
      "raw_author_name": "Josie Diorio",
      "raw_affiliation_strings": [
        "D. Liu, J. Diorio, B. Tannenbaum, C. Caldji, D. Francis, A. Freedman, S. Sharma, D. Pearson, M. J. Meaney, Developmental Neuroendocrinology Laboratory, Douglas Hospital Research Center, Departments of Psychiatry, and Neurology and Neurosurgery, Faculty of Medicine, McGill University, Montreal, Canada H4H 1R3.",
        "P. M. Plotsky, Department of Psychiatry and Behavioral Science, Emory University, Atlanta, GA 30322, USA."
      ],
      "affiliations": [
        {
          "raw_affiliation_string": "D. Liu, J. Diorio, B. Tannenbaum, C. Caldji, D. Francis, A. Freedman, S. Sharma, D. Pearson, M. J. Meaney, Developmental Neuroendocrinology Laboratory, Douglas Hospital Research Center, Departments of Psychiatry, and Neurology and Neurosurgery, Faculty of Medicine, McGill University, Montreal, Canada H4H 1R3.",
          "institution_ids": [
            "https://openalex.org/I5023651",
            "https://openalex.org/I2799434747"
          ]
        },
        {
          "raw_affiliation_string": "P. M. Plotsky, Department of Psychiatry and Behavioral Science, Emory University, Atlanta, GA 30322, USA.",
          "institution_ids": [
            "https://openalex.org/I150468666"
          ]
        }
      ]
    },
    {
      "author_position": "middle",
      "author": {
        "id": "https://openalex.org/A5063671772",
        "display_name": "Beth Tannenbaum",
        "orcid": null
      },
      "institutions": [
        {
          "id": "https://openalex.org/I5023651",
          "display_name": "McGill University",
          "ror": "https://ror.org/01pxwe438",
          "country_code": "CA",
          "type": "funder",
          "lineage": [
            "https://openalex.org/I5023651"
          ]
        },
        {
          "id": "https://openalex.org/I2799434747",
          "display_name": "Douglas Mental Health University Institute",
          "ror": "https://ror.org/05dk2r620",
          "country_code": "CA",
          "type": "healthcare",
          "lineage": [
            "https://openalex.org/I2799434747"
          ]
        },
        {
          "id": "https://openalex.org/I150468666",
          "display_name": "Emory University",
          "ror": "https://ror.org/03czfpz43",
          "country_code": "US",
          "type": "funder",
          "lineage": [
            "https://openalex.org/I150468666"
          ]
        }
      ],
      "countries": [
        "CA",
        "US"
      ],
      "is_corresponding": false,
      "raw_author_name": "Beth Tannenbaum",
      "raw_affiliation_strings": [
        "D. Liu, J. Diorio, B. Tannenbaum, C. Caldji, D. Francis, A. Freedman, S. Sharma, D. Pearson, M. J. Meaney, Developmental Neuroendocrinology Laboratory, Douglas Hospital Research Center, Departments of Psychiatry, and Neurology and Neurosurgery, Faculty of Medicine, McGill University, Montreal, Canada H4H 1R3.",
        "P. M. Plotsky, Department of Psychiatry and Behavioral Science, Emory University, Atlanta, GA 30322, USA."
      ],
      "affiliations": [
        {
          "raw_affiliation_string": "D. Liu, J. Diorio, B. Tannenbaum, C. Caldji, D. Francis, A. Freedman, S. Sharma, D. Pearson, M. J. Meaney, Developmental Neuroendocrinology Laboratory, Douglas Hospital Research Center, Departments of Psychiatry, and Neurology and Neurosurgery, Faculty of Medicine, McGill University, Montreal, Canada H4H 1R3.",
          "institution_ids": [
            "https://openalex.org/I5023651",
            "https://openalex.org/I2799434747"
          ]
        },
        {
          "raw_affiliation_string": "P. M. Plotsky, Department of Psychiatry and Behavioral Science, Emory University, Atlanta, GA 30322, USA.",
          "institution_ids": [
            "https://openalex.org/I150468666"
          ]
        }
      ]
    },
    {
      "author_position": "middle",
      "author": {
        "id": "https://openalex.org/A5058548765",
        "display_name": "Christian Caldji",
        "orcid": null
      },
      "institutions": [
        {
          "id": "https://openalex.org/I5023651",
          "display_name": "McGill University",
          "ror": "https://ror.org/01pxwe438",
          "country_code": "CA",
          "type": "funder",
          "lineage": [
            "https://openalex.org/I5023651"
          ]
        },
        {
          "id": "https://openalex.org/I2799434747",
          "display_name": "Douglas Mental Health University Institute",
          "ror": "https://ror.org/05dk2r620",
          "country_code": "CA",
          "type": "healthcare",
          "lineage": [
            "https://openalex.org/I2799434747"
          ]
        },
        {
          "id": "https://openalex.org/I150468666",
          "display_name": "Emory University",
          "ror": "https://ror.org/03czfpz43",
          "country_code": "US",
          "type": "funder",
          "lineage": [
            "https://openalex.org/I150468666"
          ]
        }
      ],
      "countries": [
        "CA",
        "US"
      ],
      "is_corresponding": false,
      "raw_author_name": "Christian Caldji",
      "raw_affiliation_strings": [
        "D. Liu, J. Diorio, B. Tannenbaum, C. Caldji, D. Francis, A. Freedman, S. Sharma, D. Pearson, M. J. Meaney, Developmental Neuroendocrinology Laboratory, Douglas Hospital Research Center, Departments of Psychiatry, and Neurology and Neurosurgery, Faculty of Medicine, McGill University, Montreal, Canada H4H 1R3.",
        "P. M. Plotsky, Department of Psychiatry and Behavioral Science, Emory University, Atlanta, GA 30322, USA."
      ],
      "affiliations": [
        {
          "raw_affiliation_string": "D. Liu, J. Diorio, B. Tannenbaum, C. Caldji, D. Francis, A. Freedman, S. Sharma, D. Pearson, M. J. Meaney, Developmental Neuroendocrinology Laboratory, Douglas Hospital Research Center, Departments of Psychiatry, and Neurology and Neurosurgery, Faculty of Medicine, McGill University, Montreal, Canada H4H 1R3.",
          "institution_ids": [
            "https://openalex.org/I5023651",
            "https://openalex.org/I2799434747"
          ]
        },
        {
          "raw_affiliation_string": "P. M. Plotsky, Department of Psychiatry and Behavioral Science, Emory University, Atlanta, GA 30322, USA.",
          "institution_ids": [
            "https://openalex.org/I150468666"
          ]
        }
      ]
    },
    {
      "author_position": "middle",
      "author": {
        "id": "https://openalex.org/A5111697302",
        "display_name": "Darlene Francis",
        "orcid": null
      },
      "institutions": [
        {
          "id": "https://openalex.org/I2799434747",
          "display_name": "Douglas Mental Health University Institute",
          "ror": "https://ror.org/05dk2r620",
          "country_code": "CA",
          "type": "healthcare",
          "lineage": [
            "https://openalex.org/I2799434747"
          ]
        },
        {
          "id": "https://openalex.org/I5023651",
          "display_name": "McGill University",
          "ror": "https://ror.org/01pxwe438",
          "country_code": "CA",
          "type": "funder",
          "lineage": [
            "https://openalex.org/I5023651"
          ]
        },
        {
          "id": "https://openalex.org/I150468666",
          "display_name": "Emory University",
          "ror": "https://ror.org/03czfpz43",
          "country_code": "US",
          "type": "funder",
          "lineage": [
            "https://openalex.org/I150468666"
          ]
        }
      ],
      "countries": [
        "CA",
        "US"
      ],
      "is_corresponding": false,
      "raw_author_name": "Darlene Francis",
      "raw_affiliation_strings": [
        "D. Liu, J. Diorio, B. Tannenbaum, C. Caldji, D. Francis, A. Freedman, S. Sharma, D. Pearson, M. J. Meaney, Developmental Neuroendocrinology Laboratory, Douglas Hospital Research Center, Departments of Psychiatry, and Neurology and Neurosurgery, Faculty of Medicine, McGill University, Montreal, Canada H4H 1R3.",
        "P. M. Plotsky, Department of Psychiatry and Behavioral Science, Emory University, Atlanta, GA 30322, USA."
      ],
      "affiliations": [
        {
          "raw_affiliation_string": "D. Liu, J. Diorio, B. Tannenbaum, C. Caldji, D. Francis, A. Freedman, S. Sharma, D. Pearson, M. J. Meaney, Developmental Neuroendocrinology Laboratory, Douglas Hospital Research Center, Departments of Psychiatry, and Neurology and Neurosurgery, Faculty of Medicine, McGill University, Montreal, Canada H4H 1R3.",
          "institution_ids": [
            "https://openalex.org/I2799434747",
            "https://openalex.org/I5023651"
          ]
        },
        {
          "raw_affiliation_string": "P. M. Plotsky, Department of Psychiatry and Behavioral Science, Emory University, Atlanta, GA 30322, USA.",
          "institution_ids": [
            "https://openalex.org/I150468666"
          ]
        }
      ]
    },
    {
      "author_position": "middle",
      "author": {
        "id": "https://openalex.org/A5087771781",
        "display_name": "Alison Freedman",
        "orcid": null
      },
      "institutions": [
        {
          "id": "https://openalex.org/I5023651",
          "display_name": "McGill University",
          "ror": "https://ror.org/01pxwe438",
          "country_code": "CA",
          "type": "funder",
          "lineage": [
            "https://openalex.org/I5023651"
          ]
        },
        {
          "id": "https://openalex.org/I2799434747",
          "display_name": "Douglas Mental Health University Institute",
          "ror": "https://ror.org/05dk2r620",
          "country_code": "CA",
          "type": "healthcare",
          "lineage": [
            "https://openalex.org/I2799434747"
          ]
        },
        {
          "id": "https://openalex.org/I150468666",
          "display_name": "Emory University",
          "ror": "https://ror.org/03czfpz43",
          "country_code": "US",
          "type": "funder",
          "lineage": [
            "https://openalex.org/I150468666"
          ]
        }
      ],
      "countries": [
        "CA",
        "US"
      ],
      "is_corresponding": false,
      "raw_author_name": "Alison Freedman",
      "raw_affiliation_strings": [
        "D. Liu, J. Diorio, B. Tannenbaum, C. Caldji, D. Francis, A. Freedman, S. Sharma, D. Pearson, M. J. Meaney, Developmental Neuroendocrinology Laboratory, Douglas Hospital Research Center, Departments of Psychiatry, and Neurology and Neurosurgery, Faculty of Medicine, McGill University, Montreal, Canada H4H 1R3.",
        "P. M. Plotsky, Department of Psychiatry and Behavioral Science, Emory University, Atlanta, GA 30322, USA."
      ],
      "affiliations": [
        {
          "raw_affiliation_string": "D. Liu, J. Diorio, B. Tannenbaum, C. Caldji, D. Francis, A. Freedman, S. Sharma, D. Pearson, M. J. Meaney, Developmental Neuroendocrinology Laboratory, Douglas Hospital Research Center, Departments of Psychiatry, and Neurology and Neurosurgery, Faculty of Medicine, McGill University, Montreal, Canada H4H 1R3.",
          "institution_ids": [
            "https://openalex.org/I5023651",
            "https://openalex.org/I2799434747"
          ]
        },
        {
          "raw_affiliation_string": "P. M. Plotsky, Department of Psychiatry and Behavioral Science, Emory University, Atlanta, GA 30322, USA.",
          "institution_ids": [
            "https://openalex.org/I150468666"
          ]
        }
      ]
    },
    {
      "author_position": "middle",
      "author": {
        "id": "https://openalex.org/A5100863377",
        "display_name": "Shakti Sharma",
        "orcid": null
      },
      "institutions": [
        {
          "id": "https://openalex.org/I150468666",
          "display_name": "Emory University",
          "ror": "https://ror.org/03czfpz43",
          "country_code": "US",
          "type": "funder",
          "lineage": [
            "https://openalex.org/I150468666"
          ]
        },
        {
          "id": "https://openalex.org/I5023651",
          "display_name": "McGill University",
          "ror": "https://ror.org/01pxwe438",
          "country_code": "CA",
          "type": "funder",
          "lineage": [
            "https://openalex.org/I5023651"
          ]
        },
        {
          "id": "https://openalex.org/I2799434747",
          "display_name": "Douglas Mental Health University Institute",
          "ror": "https://ror.org/05dk2r620",
          "country_code": "CA",
          "type": "healthcare",
          "lineage": [
            "https://openalex.org/I2799434747"
          ]
        }
      ],
      "countries": [
        "CA",
        "US"
      ],
      "is_corresponding": false,
      "raw_author_name": "Shakti Sharma",
      "raw_affiliation_strings": [
        "D. Liu, J. Diorio, B. Tannenbaum, C. Caldji, D. Francis, A. Freedman, S. Sharma, D. Pearson, M. J. Meaney, Developmental Neuroendocrinology Laboratory, Douglas Hospital Research Center, Departments of Psychiatry, and Neurology and Neurosurgery, Faculty of Medicine, McGill University, Montreal, Canada H4H 1R3.",
        "P. M. Plotsky, Department of Psychiatry and Behavioral Science, Emory University, Atlanta, GA 30322, USA."
      ],
      "affiliations": [
        {
          "raw_affiliation_string": "P. M. Plotsky, Department of Psychiatry and Behavioral Science, Emory University, Atlanta, GA 30322, USA.",
          "institution_ids": [
            "https://openalex.org/I150468666"
          ]
        },
        {
          "raw_affiliation_string": "D. Liu, J. Diorio, B. Tannenbaum, C. Caldji, D. Francis, A. Freedman, S. Sharma, D. Pearson, M. J. Meaney, Developmental Neuroendocrinology Laboratory, Douglas Hospital Research Center, Departments of Psychiatry, and Neurology and Neurosurgery, Faculty of Medicine, McGill University, Montreal, Canada H4H 1R3.",
          "institution_ids": [
            "https://openalex.org/I5023651",
            "https://openalex.org/I2799434747"
          ]
        }
      ]
    },
    {
      "author_position": "middle",
      "author": {
        "id": "https://openalex.org/A5081010890",
        "display_name": "Deborah A. Pearson",
        "orcid": "https://orcid.org/0000-0003-2047-1013"
      },
      "institutions": [
        {
          "id": "https://openalex.org/I2799434747",
          "display_name": "Douglas Mental Health University Institute",
          "ror": "https://ror.org/05dk2r620",
          "country_code": "CA",
          "type": "healthcare",
          "lineage": [
            "https://openalex.org/I2799434747"
          ]
        },
        {
          "id": "https://openalex.org/I5023651",
          "display_name": "McGill University",
          "ror": "https://ror.org/01pxwe438",
          "country_code": "CA",
          "type": "funder",
          "lineage": [
            "https://openalex.org/I5023651"
          ]
        },
        {
          "id": "https://openalex.org/I150468666",
          "display_name": "Emory University",
          "ror": "https://ror.org/03czfpz43",
          "country_code": "US",
          "type": "funder",
          "lineage": [
            "https://openalex.org/I150468666"
          ]
        }
      ],
      "countries": [
        "CA",
        "US"
      ],
      "is_corresponding": false,
      "raw_author_name": "Deborah Pearson",
      "raw_affiliation_strings": [
        "D. Liu, J. Diorio, B. Tannenbaum, C. Caldji, D. Francis, A. Freedman, S. Sharma, D. Pearson, M. J. Meaney, Developmental Neuroendocrinology Laboratory, Douglas Hospital Research Center, Departments of Psychiatry, and Neurology and Neurosurgery, Faculty of Medicine, McGill University, Montreal, Canada H4H 1R3.",
        "P. M. Plotsky, Department of Psychiatry and Behavioral Science, Emory University, Atlanta, GA 30322, USA."
      ],
      "affiliations": [
        {
          "raw_affiliation_string": "D. Liu, J. Diorio, B. Tannenbaum, C. Caldji, D. Francis, A. Freedman, S. Sharma, D. Pearson, M. J. Meaney, Developmental Neuroendocrinology Laboratory, Douglas Hospital Research Center, Departments of Psychiatry, and Neurology and Neurosurgery, Faculty of Medicine, McGill University, Montreal, Canada H4H 1R3.",
          "institution_ids": [
            "https://openalex.org/I2799434747",
            "https://openalex.org/I5023651"
          ]
        },
        {
          "raw_affiliation_string": "P. M. Plotsky, Department of Psychiatry and Behavioral Science, Emory University, Atlanta, GA 30322, USA.",
          "institution_ids": [
            "https://openalex.org/I150468666"
          ]
        }
      ]
    },
    {
      "author_position": "middle",
      "author": {
        "id": "https://openalex.org/A5004391355",
        "display_name": "Paul M. Plotsky",
        "orcid": null
      },
      "institutions": [
        {
          "id": "https://openalex.org/I150468666",
          "display_name": "Emory University",
          "ror": "https://ror.org/03czfpz43",
          "country_code": "US",
          "type": "funder",
          "lineage": [
            "https://openalex.org/I150468666"
          ]
        },
        {
          "id": "https://openalex.org/I5023651",
          "display_name": "McGill University",
          "ror": "https://ror.org/01pxwe438",
          "country_code": "CA",
          "type": "funder",
          "lineage": [
            "https://openalex.org/I5023651"
          ]
        },
        {
          "id": "https://openalex.org/I2799434747",
          "display_name": "Douglas Mental Health University Institute",
          "ror": "https://ror.org/05dk2r620",
          "country_code": "CA",
          "type": "healthcare",
          "lineage": [
            "https://openalex.org/I2799434747"
          ]
        }
      ],
      "countries": [
        "CA",
        "US"
      ],
      "is_corresponding": false,
      "raw_author_name": "Paul M. Plotsky",
      "raw_affiliation_strings": [
        "D. Liu, J. Diorio, B. Tannenbaum, C. Caldji, D. Francis, A. Freedman, S. Sharma, D. Pearson, M. J. Meaney, Developmental Neuroendocrinology Laboratory, Douglas Hospital Research Center, Departments of Psychiatry, and Neurology and Neurosurgery, Faculty of Medicine, McGill University, Montreal, Canada H4H 1R3.",
        "P. M. Plotsky, Department of Psychiatry and Behavioral Science, Emory University, Atlanta, GA 30322, USA."
      ],
      "affiliations": [
        {
          "raw_affiliation_string": "P. M. Plotsky, Department of Psychiatry and Behavioral Science, Emory University, Atlanta, GA 30322, USA.",
          "institution_ids": [
            "https://openalex.org/I150468666"
          ]
        },
        {
          "raw_affiliation_string": "D. Liu, J. Diorio, B. Tannenbaum, C. Caldji, D. Francis, A. Freedman, S. Sharma, D. Pearson, M. J. Meaney, Developmental Neuroendocrinology Laboratory, Douglas Hospital Research Center, Departments of Psychiatry, and Neurology and Neurosurgery, Faculty of Medicine, McGill University, Montreal, Canada H4H 1R3.",
          "institution_ids": [
            "https://openalex.org/I5023651",
            "https://openalex.org/I2799434747"
          ]
        }
      ]
    },
    {
      "author_position": "last",
      "author": {
        "id": "https://openalex.org/A5034400760",
        "display_name": "Michael J. Meaney",
        "orcid": "https://orcid.org/0000-0002-8605-1997"
      },
      "institutions": [
        {
          "id": "https://openalex.org/I5023651",
          "display_name": "McGill University",
          "ror": "https://ror.org/01pxwe438",
          "country_code": "CA",
          "type": "funder",
          "lineage": [
            "https://openalex.org/I5023651"
          ]
        },
        {
          "id": "https://openalex.org/I2799434747",
          "display_name": "Douglas Mental Health University Institute",
          "ror": "https://ror.org/05dk2r620",
          "country_code": "CA",
          "type": "healthcare",
          "lineage": [
            "https://openalex.org/I2799434747"
          ]
        },
        {
          "id": "https://openalex.org/I150468666",
          "display_name": "Emory University",
          "ror": "https://ror.org/03czfpz43",
          "country_code": "US",
          "type": "funder",
          "lineage": [
            "https://openalex.org/I150468666"
          ]
        }
      ],
      "countries": [
        "CA",
        "US"
      ],
      "is_corresponding": false,
      "raw_author_name": "Michael J. Meaney",
      "raw_affiliation_strings": [
        "D. Liu, J. Diorio, B. Tannenbaum, C. Caldji, D. Francis, A. Freedman, S. Sharma, D. Pearson, M. J. Meaney, Developmental Neuroendocrinology Laboratory, Douglas Hospital Research Center, Departments of Psychiatry, and Neurology and Neurosurgery, Faculty of Medicine, McGill University, Montreal, Canada H4H 1R3.",
        "P. M. Plotsky, Department of Psychiatry and Behavioral Science, Emory University, Atlanta, GA 30322, USA."
      ],
      "affiliations": [
        {
          "raw_affiliation_string": "D. Liu, J. Diorio, B. Tannenbaum, C. Caldji, D. Francis, A. Freedman, S. Sharma, D. Pearson, M. J. Meaney, Developmental Neuroendocrinology Laboratory, Douglas Hospital Research Center, Departments of Psychiatry, and Neurology and Neurosurgery, Faculty of Medicine, McGill University, Montreal, Canada H4H 1R3.",
          "institution_ids": [
            "https://openalex.org/I5023651",
            "https://openalex.org/I2799434747"
          ]
        },
        {
          "raw_affiliation_string": "P. M. Plotsky, Department of Psychiatry and Behavioral Science, Emory University, Atlanta, GA 30322, USA.",
          "institution_ids": [
            "https://openalex.org/I150468666"
          ]
        }
      ]
    }
  ],
  "institution_assertions": [],
  "countries_distinct_count": 2,
  "institutions_distinct_count": 3,
  "corresponding_author_ids": [],
  "corresponding_institution_ids": [],
  "apc_list": null,
  "apc_paid": null,
  "fwci": 26.118,
  "has_fulltext": true,
  "fulltext_origin": "ngrams",
  "cited_by_count": 3156,
  "citation_normalized_percentile": {
    "value": 0.998289,
    "is_in_top_1_percent": true,
    "is_in_top_10_percent": true
  },
  "cited_by_percentile_year": {
    "min": 99,
    "max": 100
  },
  "biblio": {
    "volume": "277",
    "issue": "5332",
    "first_page": "1659",
    "last_page": "1662"
  },
  "is_retracted": false,
  "is_paratext": false,
  "primary_topic": {
    "id": "https://openalex.org/T10529",
    "display_name": "Stress Responses and Cortisol",
    "score": 0.9999,
    "subfield": {
      "id": "https://openalex.org/subfields/2802",
      "display_name": "Behavioral Neuroscience"
    },
    "field": {
      "id": "https://openalex.org/fields/28",
      "display_name": "Neuroscience"
    },
    "domain": {
      "id": "https://openalex.org/domains/1",
      "display_name": "Life Sciences"
    }
  },
  "topics": [
    {
      "id": "https://openalex.org/T10529",
      "display_name": "Stress Responses and Cortisol",
      "score": 0.9999,
      "subfield": {
        "id": "https://openalex.org/subfields/2802",
        "display_name": "Behavioral Neuroscience"
      },
      "field": {
        "id": "https://openalex.org/fields/28",
        "display_name": "Neuroscience"
      },
      "domain": {
        "id": "https://openalex.org/domains/1",
        "display_name": "Life Sciences"
      }
    },
    {
      "id": "https://openalex.org/T11541",
      "display_name": "Neuroendocrine regulation and behavior",
      "score": 0.9997,
      "subfield": {
        "id": "https://openalex.org/subfields/3207",
        "display_name": "Social Psychology"
      },
      "field": {
        "id": "https://openalex.org/fields/32",
        "display_name": "Psychology"
      },
      "domain": {
        "id": "https://openalex.org/domains/2",
        "display_name": "Social Sciences"
      }
    },
    {
      "id": "https://openalex.org/T11337",
      "display_name": "Tryptophan and brain disorders",
      "score": 0.9927,
      "subfield": {
        "id": "https://openalex.org/subfields/2803",
        "display_name": "Biological Psychiatry"
      },
      "field": {
        "id": "https://openalex.org/fields/28",
        "display_name": "Neuroscience"
      },
      "domain": {
        "id": "https://openalex.org/domains/1",
        "display_name": "Life Sciences"
      }
    }
  ],
  "keywords": [
    {
      "id": "https://openalex.org/keywords/corticosterone",
      "display_name": "Corticosterone",
      "score": 0.78349966
    },
    {
      "id": "https://openalex.org/keywords/licking",
      "display_name": "Licking",
      "score": 0.779125
    },
    {
      "id": "https://openalex.org/keywords/hypothalamic–pituitary–adrenal-axis",
      "display_name": "Hypothalamic–pituitary–adrenal axis",
      "score": 0.5516403
    },
    {
      "id": "https://openalex.org/keywords/corticotropin-releasing-hormone",
      "display_name": "Corticotropin-releasing hormone",
      "score": 0.43247014
    }
  ],
  "concepts": [
    {
      "id": "https://openalex.org/C126322002",
      "wikidata": "https://www.wikidata.org/wiki/Q11180",
      "display_name": "Internal medicine",
      "level": 1,
      "score": 0.7970928
    },
    {
      "id": "https://openalex.org/C134018914",
      "wikidata": "https://www.wikidata.org/wiki/Q162606",
      "display_name": "Endocrinology",
      "level": 1,
      "score": 0.78374517
    },
    {
      "id": "https://openalex.org/C2780352252",
      "wikidata": "https://www.wikidata.org/wiki/Q422543",
      "display_name": "Corticosterone",
      "level": 3,
      "score": 0.78349966
    },
    {
      "id": "https://openalex.org/C2780723003",
      "wikidata": "https://www.wikidata.org/wiki/Q2917928",
      "display_name": "Licking",
      "level": 2,
      "score": 0.779125
    },
    {
      "id": "https://openalex.org/C59493245",
      "wikidata": "https://www.wikidata.org/wiki/Q14877410",
      "display_name": "Glucocorticoid receptor",
      "level": 3,
      "score": 0.75366485
    },
    {
      "id": "https://openalex.org/C112672928",
      "wikidata": "https://www.wikidata.org/wiki/Q239526",
      "display_name": "Offspring",
      "level": 3,
      "score": 0.69384664
    },
    {
      "id": "https://openalex.org/C2780841215",
      "wikidata": "https://www.wikidata.org/wiki/Q422549",
      "display_name": "Glucocorticoid",
      "level": 2,
      "score": 0.6624315
    },
    {
      "id": "https://openalex.org/C2780546910",
      "wikidata": "https://www.wikidata.org/wiki/Q185690",
      "display_name": "Adrenocorticotropic hormone",
      "level": 3,
      "score": 0.61133146
    },
    {
      "id": "https://openalex.org/C148762608",
      "wikidata": "https://www.wikidata.org/wiki/Q3748185",
      "display_name": "Hippocampal formation",
      "level": 2,
      "score": 0.58306706
    },
    {
      "id": "https://openalex.org/C2779146795",
      "wikidata": "https://www.wikidata.org/wiki/Q1369123",
      "display_name": "Hypothalamic–pituitary–adrenal axis",
      "level": 3,
      "score": 0.5516403
    },
    {
      "id": "https://openalex.org/C2777003273",
      "wikidata": "https://www.wikidata.org/wiki/Q164386",
      "display_name": "Hypothalamus",
      "level": 2,
      "score": 0.4995494
    },
    {
      "id": "https://openalex.org/C170493617",
      "wikidata": "https://www.wikidata.org/wiki/Q208467",
      "display_name": "Receptor",
      "level": 2,
      "score": 0.45972416
    },
    {
      "id": "https://openalex.org/C71315377",
      "wikidata": "https://www.wikidata.org/wiki/Q11364",
      "display_name": "Hormone",
      "level": 2,
      "score": 0.43853346
    },
    {
      "id": "https://openalex.org/C2778458438",
      "wikidata": "https://www.wikidata.org/wiki/Q386664",
      "display_name": "Corticotropin-releasing hormone",
      "level": 3,
      "score": 0.43247014
    },
    {
      "id": "https://openalex.org/C15744967",
      "wikidata": "https://www.wikidata.org/wiki/Q9418",
      "display_name": "Psychology",
      "level": 0,
      "score": 0.35301512
    },
    {
      "id": "https://openalex.org/C86803240",
      "wikidata": "https://www.wikidata.org/wiki/Q420",
      "display_name": "Biology",
      "level": 0,
      "score": 0.30930948
    },
    {
      "id": "https://openalex.org/C71924100",
      "wikidata": "https://www.wikidata.org/wiki/Q11190",
      "display_name": "Medicine",
      "level": 0,
      "score": 0.29955602
    },
    {
      "id": "https://openalex.org/C2779234561",
      "wikidata": "https://www.wikidata.org/wiki/Q11995",
      "display_name": "Pregnancy",
      "level": 2,
      "score": 0.1746
    },
    {
      "id": "https://openalex.org/C54355233",
      "wikidata": "https://www.wikidata.org/wiki/Q7162",
      "display_name": "Genetics",
      "level": 1,
      "score": 0.0
    }
  ],
  "mesh": [
    {
      "descriptor_ui": "D006624",
      "descriptor_name": "Hippocampus",
      "qualifier_ui": "Q000502",
      "qualifier_name": "physiology",
      "is_major_topic": true
    },
    {
      "descriptor_ui": "D007030",
      "descriptor_name": "Hypothalamo-Hypophyseal System",
      "qualifier_ui": "Q000502",
      "qualifier_name": "physiology",
      "is_major_topic": true
    },
    {
      "descriptor_ui": "D008425",
      "descriptor_name": "Maternal Behavior",
      "qualifier_ui": "",
      "qualifier_name": null,
      "is_major_topic": true
    },
    {
      "descriptor_ui": "D010913",
      "descriptor_name": "Pituitary-Adrenal System",
      "qualifier_ui": "Q000502",
      "qualifier_name": "physiology",
      "is_major_topic": true
    },
    {
      "descriptor_ui": "D011965",
      "descriptor_name": "Receptors, Glucocorticoid",
      "qualifier_ui": "Q000378",
      "qualifier_name": "metabolism",
      "is_major_topic": true
    },
    {
      "descriptor_ui": "D013312",
      "descriptor_name": "Stress, Physiological",
      "qualifier_ui": "Q000503",
      "qualifier_name": "physiopathology",
      "is_major_topic": true
    },
    {
      "descriptor_ui": "D000324",
      "descriptor_name": "Adrenocorticotropic Hormone",
      "qualifier_ui": "Q000097",
      "qualifier_name": "blood",
      "is_major_topic": false
    },
    {
      "descriptor_ui": "D000324",
      "descriptor_name": "Adrenocorticotropic Hormone",
      "qualifier_ui": "",
      "qualifier_name": null,
      "is_major_topic": false
    },
    {
      "descriptor_ui": "D000818",
      "descriptor_name": "Animals",
      "qualifier_ui": "",
      "qualifier_name": null,
      "is_major_topic": false
    },
    {
      "descriptor_ui": "D000831",
      "descriptor_name": "Animals, Newborn",
      "qualifier_ui": "",
      "qualifier_name": null,
      "is_major_topic": false
    },
    {
      "descriptor_ui": "D003345",
      "descriptor_name": "Corticosterone",
      "qualifier_ui": "Q000097",
      "qualifier_name": "blood",
      "is_major_topic": false
    },
    {
      "descriptor_ui": "D003345",
      "descriptor_name": "Corticosterone",
      "qualifier_ui": "Q000494",
      "qualifier_name": "pharmacology",
      "is_major_topic": false
    },
    {
      "descriptor_ui": "D003345",
      "descriptor_name": "Corticosterone",
      "qualifier_ui": "",
      "qualifier_name": null,
      "is_major_topic": false
    },
    {
      "descriptor_ui": "D003346",
      "descriptor_name": "Corticotropin-Releasing Hormone",
      "qualifier_ui": "Q000235",
      "qualifier_name": "genetics",
      "is_major_topic": false
    },
    {
      "descriptor_ui": "D003346",
      "descriptor_name": "Corticotropin-Releasing Hormone",
      "qualifier_ui": "",
      "qualifier_name": null,
      "is_major_topic": false
    },
    {
      "descriptor_ui": "D005246",
      "descriptor_name": "Feedback",
      "qualifier_ui": "",
      "qualifier_name": null,
      "is_major_topic": false
    },
    {
      "descriptor_ui": "D005260",
      "descriptor_name": "Female",
      "qualifier_ui": "",
      "qualifier_name": null,
      "is_major_topic": false
    },
    {
      "descriptor_ui": "D005786",
      "descriptor_name": "Gene Expression Regulation",
      "qualifier_ui": "",
      "qualifier_name": null,
      "is_major_topic": false
    },
    {
      "descriptor_ui": "D006120",
      "descriptor_name": "Grooming",
      "qualifier_ui": "",
      "qualifier_name": null,
      "is_major_topic": false
    },
    {
      "descriptor_ui": "D006234",
      "descriptor_name": "Handling, Psychological",
      "qualifier_ui": "",
      "qualifier_name": null,
      "is_major_topic": false
    },
    {
      "descriptor_ui": "D006624",
      "descriptor_name": "Hippocampus",
      "qualifier_ui": "",
      "qualifier_name": null,
      "is_major_topic": false
    },
    {
      "descriptor_ui": "D007030",
      "descriptor_name": "Hypothalamo-Hypophyseal System",
      "qualifier_ui": "",
      "qualifier_name": null,
      "is_major_topic": false
    },
    {
      "descriptor_ui": "D010913",
      "descriptor_name": "Pituitary-Adrenal System",
      "qualifier_ui": "",
      "qualifier_name": null,
      "is_major_topic": false
    },
    {
      "descriptor_ui": "D012333",
      "descriptor_name": "RNA, Messenger",
      "qualifier_ui": "Q000235",
      "qualifier_name": "genetics",
      "is_major_topic": false
    },
    {
      "descriptor_ui": "D012333",
      "descriptor_name": "RNA, Messenger",
      "qualifier_ui": "Q000378",
      "qualifier_name": "metabolism",
      "is_major_topic": false
    },
    {
      "descriptor_ui": "D012333",
      "descriptor_name": "RNA, Messenger",
      "qualifier_ui": "",
      "qualifier_name": null,
      "is_major_topic": false
    },
    {
      "descriptor_ui": "D051381",
      "descriptor_name": "Rats",
      "qualifier_ui": "",
      "qualifier_name": null,
      "is_major_topic": false
    },
    {
      "descriptor_ui": "D011965",
      "descriptor_name": "Receptors, Glucocorticoid",
      "qualifier_ui": "Q000235",
      "qualifier_name": "genetics",
      "is_major_topic": false
    },
    {
      "descriptor_ui": "D011965",
      "descriptor_name": "Receptors, Glucocorticoid",
      "qualifier_ui": "",
      "qualifier_name": null,
      "is_major_topic": false
    },
    {
      "descriptor_ui": "D013312",
      "descriptor_name": "Stress, Physiological",
      "qualifier_ui": "",
      "qualifier_name": null,
      "is_major_topic": false
    }
  ],
  "locations_count": 2,
  "locations": [
    {
      "is_oa": false,
      "landing_page_url": "https://doi.org/10.1126/science.277.5332.1659",
      "pdf_url": null,
      "source": {
        "id": "https://openalex.org/S3880285",
        "display_name": "Science",
        "issn_l": "0036-8075",
        "issn": [
          "0036-8075",
          "1095-9203"
        ],
        "is_oa": false,
        "is_in_doaj": false,
        "is_indexed_in_scopus": true,
        "is_core": true,
        "host_organization": "https://openalex.org/P4310315823",
        "host_organization_name": "American Association for the Advancement of Science",
        "host_organization_lineage": [
          "https://openalex.org/P4310315823"
        ],
        "host_organization_lineage_names": [
          "American Association for the Advancement of Science"
        ],
        "type": "journal"
      },
      "license": null,
      "license_id": null,
      "version": null,
      "is_accepted": false,
      "is_published": false
    },
    {
      "is_oa": false,
      "landing_page_url": "https://pubmed.ncbi.nlm.nih.gov/9287218",
      "pdf_url": null,
      "source": {
        "id": "https://openalex.org/S4306525036",
        "display_name": "PubMed",
        "issn_l": null,
        "issn": null,
        "is_oa": false,
        "is_in_doaj": false,
        "is_indexed_in_scopus": false,
        "is_core": false,
        "host_organization": "https://openalex.org/I1299303238",
        "host_organization_name": "National Institutes of Health",
        "host_organization_lineage": [
          "https://openalex.org/I1299303238"
        ],
        "host_organization_lineage_names": [
          "National Institutes of Health"
        ],
        "type": "repository"
      },
      "license": null,
      "license_id": null,
      "version": null,
      "is_accepted": false,
      "is_published": false
    }
  ],
  "best_oa_location": null,
  "sustainable_development_goals": [
    {
      "score": 0.55,
      "id": "https://metadata.un.org/sdg/3",
      "display_name": "Good health and well-being"
    }
  ],
  "grants": [],
  "datasets": [],
  "versions": [],
  "referenced_works_count": 51,
  "referenced_works": [
    "https://openalex.org/W1587738994",
    "https://openalex.org/W1593241900",
    "https://openalex.org/W1607238413",
    "https://openalex.org/W177049143",
    "https://openalex.org/W1965045797",
    "https://openalex.org/W1966579845",
    "https://openalex.org/W1971037494",
    "https://openalex.org/W1974571140",
    "https://openalex.org/W1981480708",
    "https://openalex.org/W1984427714",
    "https://openalex.org/W1987521821",
    "https://openalex.org/W1993736539",
    "https://openalex.org/W2010279188",
    "https://openalex.org/W2014619876",
    "https://openalex.org/W2016790673",
    "https://openalex.org/W2018919319",
    "https://openalex.org/W2027760035",
    "https://openalex.org/W2035868356",
    "https://openalex.org/W2036587591",
    "https://openalex.org/W2042623677",
    "https://openalex.org/W2043110076",
    "https://openalex.org/W2045202059",
    "https://openalex.org/W2046177214",
    "https://openalex.org/W2047620892",
    "https://openalex.org/W2055238225",
    "https://openalex.org/W2056898436",
    "https://openalex.org/W2059836920",
    "https://openalex.org/W2060644077",
    "https://openalex.org/W2076018826",
    "https://openalex.org/W2082181529",
    "https://openalex.org/W2083637784",
    "https://openalex.org/W2087368034",
    "https://openalex.org/W2087676383",
    "https://openalex.org/W2091655849",
    "https://openalex.org/W2097726093",
    "https://openalex.org/W2108415323",
    "https://openalex.org/W2136709982",
    "https://openalex.org/W2143837759",
    "https://openalex.org/W2145864819",
    "https://openalex.org/W2146238873",
    "https://openalex.org/W2146389083",
    "https://openalex.org/W2151301727",
    "https://openalex.org/W2165563122",
    "https://openalex.org/W296275133",
    "https://openalex.org/W313547275",
    "https://openalex.org/W4233555272",
    "https://openalex.org/W4237583988",
    "https://openalex.org/W4248118235",
    "https://openalex.org/W4248192322",
    "https://openalex.org/W4249690187",
    "https://openalex.org/W79413183"
  ],
  "related_works": [
    "https://openalex.org/W4291343341",
    "https://openalex.org/W4235631255",
    "https://openalex.org/W2102405735",
    "https://openalex.org/W2100950207",
    "https://openalex.org/W2094260805",
    "https://openalex.org/W2067083942",
    "https://openalex.org/W2060007046",
    "https://openalex.org/W2053089930",
    "https://openalex.org/W2024235957",
    "https://openalex.org/W1987134707"
  ],
  "abstract_inverted_index": {
    "Variations": [
      0
    ],
    "in": [
      1,
      10,
      15,
      100
    ],
    "maternal": [
      2,
      78,
      91
    ],
    "care": [
      3
    ],
    "affect": [
      4
    ],
    "the": [
      5,
      19,
      32,
      75,
      101
    ],
    "development": [
      6
    ],
    "of": [
      7,
      21,
      29,
      36,
      63,
      77
    ],
    "individual": [
      8
    ],
    "differences": [
      9
    ],
    "neuroendocrine": [
      11
    ],
    "responses": [
      12,
      45,
      97
    ],
    "to": [
      13,
      46,
      94,
      98
    ],
    "stress": [
      14,
      99
    ],
    "rats.": [
      16
    ],
    "As": [
      17
    ],
    "adults,": [
      18
    ],
    "offspring": [
      20
    ],
    "mothers": [
      22
    ],
    "that": [
      23,
      90
    ],
    "exhibited": [
      24
    ],
    "more": [
      25
    ],
    "licking": [
      26,
      79
    ],
    "and": [
      27,
      43,
      60,
      80
    ],
    "grooming": [
      28,
      81
    ],
    "pups": [
      30
    ],
    "during": [
      31
    ],
    "first": [
      33
    ],
    "10": [
      34
    ],
    "days": [
      35
    ],
    "life": [
      37
    ],
    "showed": [
      38
    ],
    "reduced": [
      39
    ],
    "plasma": [
      40
    ],
    "adrenocorticotropic": [
      41
    ],
    "hormone": [
      42,
      66
    ],
    "corticosterone": [
      44
    ],
    "acute": [
      47
    ],
    "stress,": [
      48
    ],
    "increased": [
      49
    ],
    "hippocampal": [
      50
    ],
    "glucocorticoid": [
      51,
      57
    ],
    "receptor": [
      52
    ],
    "messenger": [
      53,
      67
    ],
    "RNA": [
      54
    ],
    "expression,": [
      55
    ],
    "enhanced": [
      56
    ],
    "feedback": [
      58
    ],
    "sensitivity,": [
      59
    ],
    "decreased": [
      61
    ],
    "levels": [
      62
    ],
    "hypothalamic": [
      64
    ],
    "corticotropin-releasing": [
      65
    ],
    "RNA.": [
      68
    ],
    "Each": [
      69
    ],
    "measure": [
      70
    ],
    "was": [
      71
    ],
    "significantly": [
      72
    ],
    "correlated": [
      73
    ],
    "with": [
      74
    ],
    "frequency": [
      76
    ],
    "(all": [
      82
    ],
    "r": [
      83
    ],
    "'s": [
      84
    ],
    "&gt;": [
      85
    ],
    "−0.6).": [
      86
    ],
    "These": [
      87
    ],
    "findings": [
      88
    ],
    "suggest": [
      89
    ],
    "behavior": [
      92
    ],
    "serves": [
      93
    ],
    "“program”": [
      95
    ],
    "hypothalamic-pituitary-adrenal": [
      96
    ],
    "offspring.": [
      102
    ]
  },
  "abstract_inverted_index_v3": null,
  "cited_by_api_url": "https://api.openalex.org/works?filter=cites:W2054692302",
  "counts_by_year": [
    {
      "year": 2025,
      "cited_by_count": 15
    },
    {
      "year": 2024,
      "cited_by_count": 45
    },
    {
      "year": 2023,
      "cited_by_count": 58
    },
    {
      "year": 2022,
      "cited_by_count": 74
    },
    {
      "year": 2021,
      "cited_by_count": 91
    },
    {
      "year": 2020,
      "cited_by_count": 141
    },
    {
      "year": 2019,
      "cited_by_count": 106
    },
    {
      "year": 2018,
      "cited_by_count": 135
    },
    {
      "year": 2017,
      "cited_by_count": 125
    },
    {
      "year": 2016,
      "cited_by_count": 150
    },
    {
      "year": 2015,
      "cited_by_count": 145
    },
    {
      "year": 2014,
      "cited_by_count": 186
    },
    {
      "year": 2013,
      "cited_by_count": 171
    },
    {
      "year": 2012,
      "cited_by_count": 177
    }
  ],
  "updated_date": "2025-06-09T20:54:56.554612",
  "created_date": "2016-06-24"
}