{
  "id": "https://openalex.org/W2071650241",
  "doi": "https://doi.org/10.1016/s0378-4347(99)00066-3",
  "title": "Screening urine for exogenous testosterone by isotope ratio mass spectrometric analysis of one pregnanediol and two androstanediols",
  "display_name": "Screening urine for exogenous testosterone by isotope ratio mass spectrometric analysis of one pregnanediol and two androstanediols",
  "publication_year": 1999,
  "publication_date": "1999-04-01",
  "ids": {
    "openalex": "https://openalex.org/W2071650241",
    "doi": "https://doi.org/10.1016/s0378-4347(99)00066-3",
    "mag": "2071650241",
    "pmid": "https://pubmed.ncbi.nlm.nih.gov/10360427"
  },
  "language": "en",
  "primary_location": {
    "is_oa": false,
    "landing_page_url": "https://doi.org/10.1016/s0378-4347(99)00066-3",
    "pdf_url": null,
    "source": {
      "id": "https://openalex.org/S14366386",
      "display_name": "Journal of Chromatography B Biomedical Sciences and Applications",
      "issn_l": "0378-4347",
      "issn": [
        "0378-4347",
        "1872-812X"
      ],
      "is_oa": false,
      "is_in_doaj": false,
      "is_indexed_in_scopus": false,
      "is_core": true,
      "host_organization": "https://openalex.org/P4310320990",
      "host_organization_name": "Elsevier BV",
      "host_organization_lineage": [
        "https://openalex.org/P4310320990"
      ],
      "host_organization_lineage_names": [
        "Elsevier BV"
      ],
      "type": "journal"
    },
    "license": null,
    "license_id": null,
    "version": null,
    "is_accepted": false,
    "is_published": false
  },
  "type": "article",
  "type_crossref": "journal-article",
  "indexed_in": [
    "crossref",
    "pubmed"
  ],
  "open_access": {
    "is_oa": false,
    "oa_status": "closed",
    "oa_url": null,
    "any_repository_has_fulltext": false
  },
  "authorships": [
    {
      "author_position": "first",
      "author": {
        "id": "https://openalex.org/A5108877523",
        "display_name": "Rodrigo Aguilera",
        "orcid": null
      },
      "institutions": [
        {
          "id": "https://openalex.org/I161318765",
          "display_name": "University of California, Los Angeles",
          "ror": "https://ror.org/046rm7j60",
          "country_code": "US",
          "type": "funder",
          "lineage": [
            "https://openalex.org/I161318765"
          ]
        }
      ],
      "countries": [
        "US"
      ],
      "is_corresponding": true,
      "raw_author_name": "Rodrigo Aguilera",
      "raw_affiliation_strings": [
        "UCLA Olympic Analytical Laboratory, Department of Molecular and Medical Pharmacology, University of California at Los Angeles, 2122 Granville Avenue, Los Angeles, CA 90025-6106, USA"
      ],
      "affiliations": [
        {
          "raw_affiliation_string": "UCLA Olympic Analytical Laboratory, Department of Molecular and Medical Pharmacology, University of California at Los Angeles, 2122 Granville Avenue, Los Angeles, CA 90025-6106, USA",
          "institution_ids": [
            "https://openalex.org/I161318765"
          ]
        }
      ]
    },
    {
      "author_position": "middle",
      "author": {
        "id": "https://openalex.org/A5041585721",
        "display_name": "Don H. Catlin",
        "orcid": null
      },
      "institutions": [
        {
          "id": "https://openalex.org/I161318765",
          "display_name": "University of California, Los Angeles",
          "ror": "https://ror.org/046rm7j60",
          "country_code": "US",
          "type": "funder",
          "lineage": [
            "https://openalex.org/I161318765"
          ]
        }
      ],
      "countries": [
        "US"
      ],
      "is_corresponding": false,
      "raw_author_name": "Don H. Catlin",
      "raw_affiliation_strings": [
        "UCLA Olympic Analytical Laboratory, Department of Medicine, University of California at Los Angeles, 2122 Granville Avenue, Los Angeles, CA 90025-6106, USA",
        "UCLA Olympic Analytical Laboratory, Department of Molecular and Medical Pharmacology, University of California at Los Angeles, 2122 Granville Avenue, Los Angeles, CA 90025-6106, USA"
      ],
      "affiliations": [
        {
          "raw_affiliation_string": "UCLA Olympic Analytical Laboratory, Department of Medicine, University of California at Los Angeles, 2122 Granville Avenue, Los Angeles, CA 90025-6106, USA",
          "institution_ids": [
            "https://openalex.org/I161318765"
          ]
        },
        {
          "raw_affiliation_string": "UCLA Olympic Analytical Laboratory, Department of Molecular and Medical Pharmacology, University of California at Los Angeles, 2122 Granville Avenue, Los Angeles, CA 90025-6106, USA",
          "institution_ids": [
            "https://openalex.org/I161318765"
          ]
        }
      ]
    },
    {
      "author_position": "middle",
      "author": {
        "id": "https://openalex.org/A5042762405",
        "display_name": "Michel Becchi",
        "orcid": null
      },
      "institutions": [
        {
          "id": "https://openalex.org/I1294671590",
          "display_name": "Centre National de la Recherche Scientifique",
          "ror": "https://ror.org/02feahw73",
          "country_code": "FR",
          "type": "government",
          "lineage": [
            "https://openalex.org/I1294671590"
          ]
        }
      ],
      "countries": [
        "FR"
      ],
      "is_corresponding": false,
      "raw_author_name": "Michel Becchi",
      "raw_affiliation_strings": [
        "Service Central d’Analyse, CNRS, BP 22, 69390 Vernaison, France"
      ],
      "affiliations": [
        {
          "raw_affiliation_string": "Service Central d’Analyse, CNRS, BP 22, 69390 Vernaison, France",
          "institution_ids": [
            "https://openalex.org/I1294671590"
          ]
        }
      ]
    },
    {
      "author_position": "middle",
      "author": {
        "id": "https://openalex.org/A5113494229",
        "display_name": "Andy Phillips",
        "orcid": null
      },
      "institutions": [
        {
          "id": "https://openalex.org/I4210150798",
          "display_name": "Wythenshawe Hospital",
          "ror": "https://ror.org/05vpsdj37",
          "country_code": "GB",
          "type": "healthcare",
          "lineage": [
            "https://openalex.org/I4210092852",
            "https://openalex.org/I4210150798"
          ]
        }
      ],
      "countries": [
        "GB"
      ],
      "is_corresponding": false,
      "raw_author_name": "Andy Phillips",
      "raw_affiliation_strings": [
        "Micromass, Wythenshawe, Manchester, UK"
      ],
      "affiliations": [
        {
          "raw_affiliation_string": "Micromass, Wythenshawe, Manchester, UK",
          "institution_ids": [
            "https://openalex.org/I4210150798"
          ]
        }
      ]
    },
    {
      "author_position": "middle",
      "author": {
        "id": "https://openalex.org/A5075031077",
        "display_name": "Cristina Wang",
        "orcid": null
      },
      "institutions": [
        {
          "id": "https://openalex.org/I2801403999",
          "display_name": "UCLA Medical Center",
          "ror": "https://ror.org/04vq5kb54",
          "country_code": "US",
          "type": "healthcare",
          "lineage": [
            "https://openalex.org/I2799798094",
            "https://openalex.org/I2801403999"
          ]
        },
        {
          "id": "https://openalex.org/I4210165985",
          "display_name": "Harbor–UCLA Medical Center",
          "ror": "https://ror.org/05h4zj272",
          "country_code": "US",
          "type": "healthcare",
          "lineage": [
            "https://openalex.org/I1328359107",
            "https://openalex.org/I4210165985"
          ]
        }
      ],
      "countries": [
        "US"
      ],
      "is_corresponding": false,
      "raw_author_name": "Cristina Wang",
      "raw_affiliation_strings": [
        "Division of Endocrinology, Department of Medicine, Harbor-UCLA Medical Center, Torrance, CA 90502, USA"
      ],
      "affiliations": [
        {
          "raw_affiliation_string": "Division of Endocrinology, Department of Medicine, Harbor-UCLA Medical Center, Torrance, CA 90502, USA",
          "institution_ids": [
            "https://openalex.org/I2801403999",
            "https://openalex.org/I4210165985"
          ]
        }
      ]
    },
    {
      "author_position": "middle",
      "author": {
        "id": "https://openalex.org/A5113630655",
        "display_name": "Ronald S. Swerdloff",
        "orcid": null
      },
      "institutions": [
        {
          "id": "https://openalex.org/I2801403999",
          "display_name": "UCLA Medical Center",
          "ror": "https://ror.org/04vq5kb54",
          "country_code": "US",
          "type": "healthcare",
          "lineage": [
            "https://openalex.org/I2799798094",
            "https://openalex.org/I2801403999"
          ]
        },
        {
          "id": "https://openalex.org/I4210165985",
          "display_name": "Harbor–UCLA Medical Center",
          "ror": "https://ror.org/05h4zj272",
          "country_code": "US",
          "type": "healthcare",
          "lineage": [
            "https://openalex.org/I1328359107",
            "https://openalex.org/I4210165985"
          ]
        }
      ],
      "countries": [
        "US"
      ],
      "is_corresponding": false,
      "raw_author_name": "Ronald S. Swerdloff",
      "raw_affiliation_strings": [
        "Division of Endocrinology, Department of Medicine, Harbor-UCLA Medical Center, Torrance, CA 90502, USA"
      ],
      "affiliations": [
        {
          "raw_affiliation_string": "Division of Endocrinology, Department of Medicine, Harbor-UCLA Medical Center, Torrance, CA 90502, USA",
          "institution_ids": [
            "https://openalex.org/I2801403999",
            "https://openalex.org/I4210165985"
          ]
        }
      ]
    },
    {
      "author_position": "middle",
      "author": {
        "id": "https://openalex.org/A5005998157",
        "display_name": "Harrison G. Pope",
        "orcid": "https://orcid.org/0000-0003-1298-6439"
      },
      "institutions": [
        {
          "id": "https://openalex.org/I2801148111",
          "display_name": "McLean Hospital",
          "ror": "https://ror.org/01kta7d96",
          "country_code": "US",
          "type": "healthcare",
          "lineage": [
            "https://openalex.org/I2801148111"
          ]
        },
        {
          "id": "https://openalex.org/I136199984",
          "display_name": "Harvard University",
          "ror": "https://ror.org/03vek6s52",
          "country_code": "US",
          "type": "funder",
          "lineage": [
            "https://openalex.org/I136199984"
          ]
        }
      ],
      "countries": [
        "US"
      ],
      "is_corresponding": false,
      "raw_author_name": "Harrison G. Pope",
      "raw_affiliation_strings": [
        "Harvard Medical School, McLean Hospital, 115 Mill Street, Belmont, MA 02178-9106, USA"
      ],
      "affiliations": [
        {
          "raw_affiliation_string": "Harvard Medical School, McLean Hospital, 115 Mill Street, Belmont, MA 02178-9106, USA",
          "institution_ids": [
            "https://openalex.org/I2801148111",
            "https://openalex.org/I136199984"
          ]
        }
      ]
    },
    {
      "author_position": "last",
      "author": {
        "id": "https://openalex.org/A5055613736",
        "display_name": "Caroline K. Hatton",
        "orcid": null
      },
      "institutions": [
        {
          "id": "https://openalex.org/I161318765",
          "display_name": "University of California, Los Angeles",
          "ror": "https://ror.org/046rm7j60",
          "country_code": "US",
          "type": "funder",
          "lineage": [
            "https://openalex.org/I161318765"
          ]
        }
      ],
      "countries": [
        "US"
      ],
      "is_corresponding": false,
      "raw_author_name": "Caroline K. Hatton",
      "raw_affiliation_strings": [
        "UCLA Olympic Analytical Laboratory, Department of Molecular and Medical Pharmacology, University of California at Los Angeles, 2122 Granville Avenue, Los Angeles, CA 90025-6106, USA"
      ],
      "affiliations": [
        {
          "raw_affiliation_string": "UCLA Olympic Analytical Laboratory, Department of Molecular and Medical Pharmacology, University of California at Los Angeles, 2122 Granville Avenue, Los Angeles, CA 90025-6106, USA",
          "institution_ids": [
            "https://openalex.org/I161318765"
          ]
        }
      ]
    }
  ],
  "institution_assertions": [],
  "countries_distinct_count": 3,
  "institutions_distinct_count": 7,
  "corresponding_author_ids": [
    "https://openalex.org/A5108877523"
  ],
  "corresponding_institution_ids": [
    "https://openalex.org/I161318765"
  ],
  "apc_list": null,
  "apc_paid": null,
  "fwci": 3.304,
  "has_fulltext": true,
  "fulltext_origin": "ngrams",
  "cited_by_count": 97,
  "citation_normalized_percentile": {
    "value": 0.846506,
    "is_in_top_1_percent": false,
    "is_in_top_10_percent": false
  },
  "cited_by_percentile_year": {
    "min": 95,
    "max": 96
  },
  "biblio": {
    "volume": "727",
    "issue": "1-2",
    "first_page": "95",
    "last_page": "105"
  },
  "is_retracted": false,
  "is_paratext": false,
  "primary_topic": {
    "id": "https://openalex.org/T11146",
    "display_name": "Hormonal and reproductive studies",
    "score": 1.0,
    "subfield": {
      "id": "https://openalex.org/subfields/2712",
      "display_name": "Endocrinology, Diabetes and Metabolism"
    },
    "field": {
      "id": "https://openalex.org/fields/27",
      "display_name": "Medicine"
    },
    "domain": {
      "id": "https://openalex.org/domains/4",
      "display_name": "Health Sciences"
    }
  },
  "topics": [
    {
      "id": "https://openalex.org/T11146",
      "display_name": "Hormonal and reproductive studies",
      "score": 1.0,
      "subfield": {
        "id": "https://openalex.org/subfields/2712",
        "display_name": "Endocrinology, Diabetes and Metabolism"
      },
      "field": {
        "id": "https://openalex.org/fields/27",
        "display_name": "Medicine"
      },
      "domain": {
        "id": "https://openalex.org/domains/4",
        "display_name": "Health Sciences"
      }
    },
    {
      "id": "https://openalex.org/T11399",
      "display_name": "Muscle metabolism and nutrition",
      "score": 0.9993,
      "subfield": {
        "id": "https://openalex.org/subfields/1307",
        "display_name": "Cell Biology"
      },
      "field": {
        "id": "https://openalex.org/fields/13",
        "display_name": "Biochemistry, Genetics and Molecular Biology"
      },
      "domain": {
        "id": "https://openalex.org/domains/1",
        "display_name": "Life Sciences"
      }
    },
    {
      "id": "https://openalex.org/T12539",
      "display_name": "Pharmacology and Obesity Treatment",
      "score": 0.9968,
      "subfield": {
        "id": "https://openalex.org/subfields/2736",
        "display_name": "Pharmacology"
      },
      "field": {
        "id": "https://openalex.org/fields/27",
        "display_name": "Medicine"
      },
      "domain": {
        "id": "https://openalex.org/domains/4",
        "display_name": "Health Sciences"
      }
    }
  ],
  "keywords": [
    {
      "id": "https://openalex.org/keywords/epitestosterone",
      "display_name": "Epitestosterone",
      "score": 0.82114637
    },
    {
      "id": "https://openalex.org/keywords/pregnane",
      "display_name": "Pregnane",
      "score": 0.6646989
    },
    {
      "id": "https://openalex.org/keywords/isotope-ratio-mass-spectrometry",
      "display_name": "Isotope-ratio mass spectrometry",
      "score": 0.5016413
    }
  ],
  "concepts": [
    {
      "id": "https://openalex.org/C2776250704",
      "wikidata": "https://www.wikidata.org/wiki/Q906054",
      "display_name": "Pregnanediol",
      "level": 3,
      "score": 0.8959337
    },
    {
      "id": "https://openalex.org/C2779341496",
      "wikidata": "https://www.wikidata.org/wiki/Q416852",
      "display_name": "Epitestosterone",
      "level": 4,
      "score": 0.82114637
    },
    {
      "id": "https://openalex.org/C2780026642",
      "wikidata": "https://www.wikidata.org/wiki/Q40924",
      "display_name": "Urine",
      "level": 2,
      "score": 0.6833592
    },
    {
      "id": "https://openalex.org/C185592680",
      "wikidata": "https://www.wikidata.org/wiki/Q2329",
      "display_name": "Chemistry",
      "level": 0,
      "score": 0.6798516
    },
    {
      "id": "https://openalex.org/C2780655410",
      "wikidata": "https://www.wikidata.org/wiki/Q2700511",
      "display_name": "Pregnane",
      "level": 2,
      "score": 0.6646989
    },
    {
      "id": "https://openalex.org/C43617362",
      "wikidata": "https://www.wikidata.org/wiki/Q170050",
      "display_name": "Chromatography",
      "level": 1,
      "score": 0.51093286
    },
    {
      "id": "https://openalex.org/C170671577",
      "wikidata": "https://www.wikidata.org/wiki/Q3966589",
      "display_name": "Isotope-ratio mass spectrometry",
      "level": 3,
      "score": 0.5016413
    },
    {
      "id": "https://openalex.org/C2779279991",
      "wikidata": "https://www.wikidata.org/wiki/Q6058681",
      "display_name": "Testosterone (patch)",
      "level": 2,
      "score": 0.47561294
    },
    {
      "id": "https://openalex.org/C134018914",
      "wikidata": "https://www.wikidata.org/wiki/Q162606",
      "display_name": "Endocrinology",
      "level": 1,
      "score": 0.35663092
    },
    {
      "id": "https://openalex.org/C123460561",
      "wikidata": "https://www.wikidata.org/wiki/Q677065",
      "display_name": "Gas chromatography",
      "level": 2,
      "score": 0.30028632
    },
    {
      "id": "https://openalex.org/C2777911890",
      "wikidata": "https://www.wikidata.org/wiki/Q62614",
      "display_name": "Androgen",
      "level": 3,
      "score": 0.24654433
    },
    {
      "id": "https://openalex.org/C71240020",
      "wikidata": "https://www.wikidata.org/wiki/Q186011",
      "display_name": "Stereochemistry",
      "level": 1,
      "score": 0.24571371
    },
    {
      "id": "https://openalex.org/C71924100",
      "wikidata": "https://www.wikidata.org/wiki/Q11190",
      "display_name": "Medicine",
      "level": 0,
      "score": 0.17850095
    },
    {
      "id": "https://openalex.org/C55493867",
      "wikidata": "https://www.wikidata.org/wiki/Q7094",
      "display_name": "Biochemistry",
      "level": 1,
      "score": 0.1598072
    },
    {
      "id": "https://openalex.org/C71315377",
      "wikidata": "https://www.wikidata.org/wiki/Q11364",
      "display_name": "Hormone",
      "level": 2,
      "score": 0.0
    }
  ],
  "mesh": [
    {
      "descriptor_ui": "D015113",
      "descriptor_name": "Androstane-3,17-diol",
      "qualifier_ui": "Q000652",
      "qualifier_name": "urine",
      "is_major_topic": true
    },
    {
      "descriptor_ui": "D004300",
      "descriptor_name": "Doping in Sports",
      "qualifier_ui": "",
      "qualifier_name": null,
      "is_major_topic": true
    },
    {
      "descriptor_ui": "D013058",
      "descriptor_name": "Mass Spectrometry",
      "qualifier_ui": "Q000379",
      "qualifier_name": "methods",
      "is_major_topic": true
    },
    {
      "descriptor_ui": "D011276",
      "descriptor_name": "Pregnanediol",
      "qualifier_ui": "Q000652",
      "qualifier_name": "urine",
      "is_major_topic": true
    },
    {
      "descriptor_ui": "D013739",
      "descriptor_name": "Testosterone",
      "qualifier_ui": "Q000652",
      "qualifier_name": "urine",
      "is_major_topic": true
    },
    {
      "descriptor_ui": "D000328",
      "descriptor_name": "Adult",
      "qualifier_ui": "",
      "qualifier_name": null,
      "is_major_topic": false
    },
    {
      "descriptor_ui": "D015113",
      "descriptor_name": "Androstane-3,17-diol",
      "qualifier_ui": "",
      "qualifier_name": null,
      "is_major_topic": false
    },
    {
      "descriptor_ui": "D015113",
      "descriptor_name": "Androstane-3,17-diol",
      "qualifier_ui": "Q000031",
      "qualifier_name": "analogs & derivatives",
      "is_major_topic": false
    },
    {
      "descriptor_ui": "D015415",
      "descriptor_name": "Biomarkers",
      "qualifier_ui": "",
      "qualifier_name": null,
      "is_major_topic": false
    },
    {
      "descriptor_ui": "D006801",
      "descriptor_name": "Humans",
      "qualifier_ui": "",
      "qualifier_name": null,
      "is_major_topic": false
    },
    {
      "descriptor_ui": "D007554",
      "descriptor_name": "Isotopes",
      "qualifier_ui": "",
      "qualifier_name": null,
      "is_major_topic": false
    },
    {
      "descriptor_ui": "D008297",
      "descriptor_name": "Male",
      "qualifier_ui": "",
      "qualifier_name": null,
      "is_major_topic": false
    },
    {
      "descriptor_ui": "D013058",
      "descriptor_name": "Mass Spectrometry",
      "qualifier_ui": "",
      "qualifier_name": null,
      "is_major_topic": false
    },
    {
      "descriptor_ui": "D008875",
      "descriptor_name": "Middle Aged",
      "qualifier_ui": "",
      "qualifier_name": null,
      "is_major_topic": false
    },
    {
      "descriptor_ui": "D011276",
      "descriptor_name": "Pregnanediol",
      "qualifier_ui": "",
      "qualifier_name": null,
      "is_major_topic": false
    },
    {
      "descriptor_ui": "D012015",
      "descriptor_name": "Reference Standards",
      "qualifier_ui": "",
      "qualifier_name": null,
      "is_major_topic": false
    },
    {
      "descriptor_ui": "D012016",
      "descriptor_name": "Reference Values",
      "qualifier_ui": "",
      "qualifier_name": null,
      "is_major_topic": false
    },
    {
      "descriptor_ui": "D013739",
      "descriptor_name": "Testosterone",
      "qualifier_ui": "",
      "qualifier_name": null,
      "is_major_topic": false
    }
  ],
  "locations_count": 4,
  "locations": [
    {
      "is_oa": false,
      "landing_page_url": "https://doi.org/10.1016/s0378-4347(99)00066-3",
      "pdf_url": null,
      "source": {
        "id": "https://openalex.org/S14366386",
        "display_name": "Journal of Chromatography B Biomedical Sciences and Applications",
        "issn_l": "0378-4347",
        "issn": [
          "0378-4347",
          "1872-812X"
        ],
        "is_oa": false,
        "is_in_doaj": false,
        "is_indexed_in_scopus": false,
        "is_core": true,
        "host_organization": "https://openalex.org/P4310320990",
        "host_organization_name": "Elsevier BV",
        "host_organization_lineage": [
          "https://openalex.org/P4310320990"
        ],
        "host_organization_lineage_names": [
          "Elsevier BV"
        ],
        "type": "journal"
      },
      "license": null,
      "license_id": null,
      "version": null,
      "is_accepted": false,
      "is_published": false
    },
    {
      "is_oa": false,
      "landing_page_url": "https://hal.science/hal-00314106",
      "pdf_url": null,
      "source": {
        "id": "https://openalex.org/S4306402512",
        "display_name": "HAL (Le Centre pour la Communication Scientifique Directe)",
        "issn_l": null,
        "issn": null,
        "is_oa": true,
        "is_in_doaj": false,
        "is_indexed_in_scopus": false,
        "is_core": false,
        "host_organization": "https://openalex.org/I1294671590",
        "host_organization_name": "Centre National de la Recherche Scientifique",
        "host_organization_lineage": [
          "https://openalex.org/I1294671590"
        ],
        "host_organization_lineage_names": [
          "Centre National de la Recherche Scientifique"
        ],
        "type": "repository"
      },
      "license": null,
      "license_id": null,
      "version": null,
      "is_accepted": false,
      "is_published": false
    },
    {
      "is_oa": false,
      "landing_page_url": "https://hal.archives-ouvertes.fr/hal-00314106",
      "pdf_url": null,
      "source": {
        "id": "https://openalex.org/S4306402512",
        "display_name": "HAL (Le Centre pour la Communication Scientifique Directe)",
        "issn_l": null,
        "issn": null,
        "is_oa": true,
        "is_in_doaj": false,
        "is_indexed_in_scopus": false,
        "is_core": false,
        "host_organization": "https://openalex.org/I1294671590",
        "host_organization_name": "Centre National de la Recherche Scientifique",
        "host_organization_lineage": [
          "https://openalex.org/I1294671590"
        ],
        "host_organization_lineage_names": [
          "Centre National de la Recherche Scientifique"
        ],
        "type": "repository"
      },
      "license": null,
      "license_id": null,
      "version": null,
      "is_accepted": false,
      "is_published": false
    },
    {
      "is_oa": false,
      "landing_page_url": "https://pubmed.ncbi.nlm.nih.gov/10360427",
      "pdf_url": null,
      "source": {
        "id": "https://openalex.org/S4306525036",
        "display_name": "PubMed",
        "issn_l": null,
        "issn": null,
        "is_oa": false,
        "is_in_doaj": false,
        "is_indexed_in_scopus": false,
        "is_core": false,
        "host_organization": "https://openalex.org/I1299303238",
        "host_organization_name": "National Institutes of Health",
        "host_organization_lineage": [
          "https://openalex.org/I1299303238"
        ],
        "host_organization_lineage_names": [
          "National Institutes of Health"
        ],
        "type": "repository"
      },
      "license": null,
      "license_id": null,
      "version": null,
      "is_accepted": false,
      "is_published": false
    }
  ],
  "best_oa_location": null,
  "sustainable_development_goals": [
    {
      "display_name": "Clean water and sanitation",
      "id": "https://metadata.un.org/sdg/6",
      "score": 0.62
    }
  ],
  "grants": [],
  "datasets": [],
  "versions": [],
  "referenced_works_count": 17,
  "referenced_works": [
    "https://openalex.org/W1496215803",
    "https://openalex.org/W1548452296",
    "https://openalex.org/W1974005559",
    "https://openalex.org/W1982698542",
    "https://openalex.org/W1996109742",
    "https://openalex.org/W2013981842",
    "https://openalex.org/W2017691886",
    "https://openalex.org/W2018680219",
    "https://openalex.org/W2022321034",
    "https://openalex.org/W2056192617",
    "https://openalex.org/W2095460495",
    "https://openalex.org/W2100157449",
    "https://openalex.org/W2143891107",
    "https://openalex.org/W2148496797",
    "https://openalex.org/W2332642482",
    "https://openalex.org/W4256065798",
    "https://openalex.org/W4302524804"
  ],
  "related_works": [
    "https://openalex.org/W2462709061",
    "https://openalex.org/W2416994976",
    "https://openalex.org/W2411778925",
    "https://openalex.org/W2069974756",
    "https://openalex.org/W2062843723",
    "https://openalex.org/W2055190216",
    "https://openalex.org/W2047176609",
    "https://openalex.org/W2035081340",
    "https://openalex.org/W2030843276",
    "https://openalex.org/W2014310809"
  ],
  "abstract_inverted_index": null,
  "abstract_inverted_index_v3": null,
  "cited_by_api_url": "https://api.openalex.org/works?filter=cites:W2071650241",
  "counts_by_year": [
    {
      "year": 2024,
      "cited_by_count": 1
    },
    {
      "year": 2022,
      "cited_by_count": 1
    },
    {
      "year": 2021,
      "cited_by_count": 1
    },
    {
      "year": 2017,
      "cited_by_count": 3
    },
    {
      "year": 2016,
      "cited_by_count": 2
    },
    {
      "year": 2014,
      "cited_by_count": 6
    },
    {
      "year": 2013,
      "cited_by_count": 3
    },
    {
      "year": 2012,
      "cited_by_count": 12
    }
  ],
  "updated_date": "2025-05-16T10:23:54.888165",
  "created_date": "2016-06-24"
}